{
"meta":{"test_sets":[],"test_metrics":[],"learn_metrics":[{"best_value":"Min","name":"RMSE"}],"launch_mode":"Train","parameters":"","iteration_count":1000,"learn_sets":["learn"],"name":"experiment"},
"iterations":[
{"learn":[14.59871775],"iteration":0,"passed_time":0.1274677737,"remaining_time":127.3403059},
{"learn":[14.22518863],"iteration":1,"passed_time":0.1290754897,"remaining_time":64.40866938},
{"learn":[13.8866124],"iteration":2,"passed_time":0.1307377067,"remaining_time":43.44849787},
{"learn":[13.52356875],"iteration":3,"passed_time":0.1323210315,"remaining_time":32.94793685},
{"learn":[13.18870211],"iteration":4,"passed_time":0.1338296687,"remaining_time":26.63210406},
{"learn":[12.9124226],"iteration":5,"passed_time":0.1353605952,"remaining_time":22.4247386},
{"learn":[12.60003351],"iteration":6,"passed_time":0.1377147562,"remaining_time":19.53582185},
{"learn":[12.32990573],"iteration":7,"passed_time":0.1398146564,"remaining_time":17.33701739},
{"learn":[12.0660619],"iteration":8,"passed_time":0.1412372342,"remaining_time":15.55178879},
{"learn":[11.77309809],"iteration":9,"passed_time":0.1423641287,"remaining_time":14.09404874},
{"learn":[11.49227636],"iteration":10,"passed_time":0.1433935459,"remaining_time":12.89238335},
{"learn":[11.26264833],"iteration":11,"passed_time":0.14437513,"remaining_time":11.8868857},
{"learn":[11.04260393],"iteration":12,"passed_time":0.1453370738,"remaining_time":11.03443783},
{"learn":[10.79916926],"iteration":13,"passed_time":0.146067674,"remaining_time":10.28733761},
{"learn":[10.5541002],"iteration":14,"passed_time":0.1468034049,"remaining_time":9.640090256},
{"learn":[10.31918115],"iteration":15,"passed_time":0.1475845161,"remaining_time":9.076447739},
{"learn":[10.10004441],"iteration":16,"passed_time":0.1483438152,"remaining_time":8.577762961},
{"learn":[9.894556723],"iteration":17,"passed_time":0.1490723981,"remaining_time":8.132727495},
{"learn":[9.690174082],"iteration":18,"passed_time":0.1497158776,"remaining_time":7.730067155},
{"learn":[9.506034866],"iteration":19,"passed_time":0.1504050421,"remaining_time":7.369847065},
{"learn":[9.338524633],"iteration":20,"passed_time":0.151044614,"remaining_time":7.041556053},
{"learn":[9.170203312],"iteration":21,"passed_time":0.1516151686,"remaining_time":6.739983406},
{"learn":[9.010299969],"iteration":22,"passed_time":0.1521678673,"remaining_time":6.463826365},
{"learn":[8.843866678],"iteration":23,"passed_time":0.1527496006,"remaining_time":6.211817093},
{"learn":[8.690548059],"iteration":24,"passed_time":0.1533907581,"remaining_time":5.982239566},
{"learn":[8.555307687],"iteration":25,"passed_time":0.1542084998,"remaining_time":5.776887646},
{"learn":[8.413851302],"iteration":26,"passed_time":0.1547767903,"remaining_time":5.577696925},
{"learn":[8.29256019],"iteration":27,"passed_time":0.1553098724,"remaining_time":5.391471283},
{"learn":[8.162193833],"iteration":28,"passed_time":0.1558370732,"remaining_time":5.217855107},
{"learn":[8.040736294],"iteration":29,"passed_time":0.1563669866,"remaining_time":5.055865899},
{"learn":[7.921220278],"iteration":30,"passed_time":0.1569011475,"remaining_time":4.904426191},
{"learn":[7.809589039],"iteration":31,"passed_time":0.1574360283,"remaining_time":4.762439857},
{"learn":[7.699675801],"iteration":32,"passed_time":0.157960814,"remaining_time":4.628730518},
{"learn":[7.60645267],"iteration":33,"passed_time":0.1584835491,"remaining_time":4.502797306},
{"learn":[7.498880302],"iteration":34,"passed_time":0.1590370079,"remaining_time":4.384877503},
{"learn":[7.401158744],"iteration":35,"passed_time":0.1595743189,"remaining_time":4.27304565},
{"learn":[7.306431077],"iteration":36,"passed_time":0.1600970027,"remaining_time":4.166849015},
{"learn":[7.223863468],"iteration":37,"passed_time":0.1606345716,"remaining_time":4.066590996},
{"learn":[7.143477682],"iteration":38,"passed_time":0.1611548136,"remaining_time":3.971019895},
{"learn":[7.062817131],"iteration":39,"passed_time":0.1616795115,"remaining_time":3.880308276},
{"learn":[6.990793435],"iteration":40,"passed_time":0.1622133859,"remaining_time":3.794210661},
{"learn":[6.931862224],"iteration":41,"passed_time":0.1627528915,"remaining_time":3.712315954},
{"learn":[6.858296558],"iteration":42,"passed_time":0.1632978154,"remaining_time":3.634325799},
{"learn":[6.786268161],"iteration":43,"passed_time":0.1638337884,"remaining_time":3.559661402},
{"learn":[6.717118549],"iteration":44,"passed_time":0.164385407,"remaining_time":3.488623637},
{"learn":[6.652948106],"iteration":45,"passed_time":0.1650896487,"remaining_time":3.423815758},
{"learn":[6.589686076],"iteration":46,"passed_time":0.1657385623,"remaining_time":3.360613828},
{"learn":[6.531283097],"iteration":47,"passed_time":0.1665291332,"remaining_time":3.302827809},
{"learn":[6.471368031],"iteration":48,"passed_time":0.1671035277,"remaining_time":3.243172547},
{"learn":[6.416481395],"iteration":49,"passed_time":0.1676926093,"remaining_time":3.186159577},
{"learn":[6.369870822],"iteration":50,"passed_time":0.1682439551,"remaining_time":3.130657125},
{"learn":[6.325678067],"iteration":51,"passed_time":0.1687926778,"remaining_time":3.077220357},
{"learn":[6.275766122],"iteration":52,"passed_time":0.1693216415,"remaining_time":3.025426311},
{"learn":[6.224773967],"iteration":53,"passed_time":0.1698561742,"remaining_time":2.975628532},
{"learn":[6.182249254],"iteration":54,"passed_time":0.1703761852,"remaining_time":2.927372637},
{"learn":[6.139904173],"iteration":55,"passed_time":0.1709093095,"remaining_time":2.881042645},
{"learn":[6.100525536],"iteration":56,"passed_time":0.1714270125,"remaining_time":2.836064435},
{"learn":[6.062568564],"iteration":57,"passed_time":0.1719487338,"remaining_time":2.792684607},
{"learn":[6.030559288],"iteration":58,"passed_time":0.1725424642,"remaining_time":2.751906081},
{"learn":[5.997931376],"iteration":59,"passed_time":0.1730734274,"remaining_time":2.711483696},
{"learn":[5.964103835],"iteration":60,"passed_time":0.1736276616,"remaining_time":2.672727447},
{"learn":[5.933729724],"iteration":61,"passed_time":0.1741587176,"remaining_time":2.634852856},
{"learn":[5.901932711],"iteration":62,"passed_time":0.1746832407,"remaining_time":2.598066612},
{"learn":[5.873727795],"iteration":63,"passed_time":0.1752053433,"remaining_time":2.562378145},
{"learn":[5.846485734],"iteration":64,"passed_time":0.1757487822,"remaining_time":2.528078636},
{"learn":[5.820630862],"iteration":65,"passed_time":0.1762710118,"remaining_time":2.494501894},
{"learn":[5.793646238],"iteration":66,"passed_time":0.1767946706,"remaining_time":2.461931756},
{"learn":[5.765388646],"iteration":67,"passed_time":0.1773161538,"remaining_time":2.430274343},
{"learn":[5.747073912],"iteration":68,"passed_time":0.1778472813,"remaining_time":2.39964955},
{"learn":[5.722315217],"iteration":69,"passed_time":0.1783611048,"remaining_time":2.369654679},
{"learn":[5.699970599],"iteration":70,"passed_time":0.1789002502,"remaining_time":2.340821584},
{"learn":[5.682732647],"iteration":71,"passed_time":0.1796253063,"remaining_time":2.315170615},
{"learn":[5.663525791],"iteration":72,"passed_time":0.1803179223,"remaining_time":2.289790602},
{"learn":[5.642381613],"iteration":73,"passed_time":0.1810415542,"remaining_time":2.265465935},
{"learn":[5.621404779],"iteration":74,"passed_time":0.1817126976,"remaining_time":2.241123271},
{"learn":[5.602460129],"iteration":75,"passed_time":0.1823182939,"remaining_time":2.216606626},
{"learn":[5.587337574],"iteration":76,"passed_time":0.1828505707,"remaining_time":2.191832166},
{"learn":[5.572393026],"iteration":77,"passed_time":0.1833688906,"remaining_time":2.167514322},
{"learn":[5.558425806],"iteration":78,"passed_time":0.1838998953,"remaining_time":2.14394688},
{"learn":[5.541518902],"iteration":79,"passed_time":0.1844203137,"remaining_time":2.120833607},
{"learn":[5.526157283],"iteration":80,"passed_time":0.1849424154,"remaining_time":2.098297281},
{"learn":[5.511746977],"iteration":81,"passed_time":0.1854985978,"remaining_time":2.076679425},
{"learn":[5.504975022],"iteration":82,"passed_time":0.1857646584,"remaining_time":2.052363756},
{"learn":[5.493980522],"iteration":83,"passed_time":0.186300797,"remaining_time":2.031565834},
{"learn":[5.480745463],"iteration":84,"passed_time":0.1868470324,"remaining_time":2.011353349},
{"learn":[5.464052013],"iteration":85,"passed_time":0.1873770037,"remaining_time":1.991425365},
{"learn":[5.449143727],"iteration":86,"passed_time":0.1878962737,"remaining_time":1.971831011},
{"learn":[5.438255432],"iteration":87,"passed_time":0.1884289811,"remaining_time":1.952809441},
{"learn":[5.425927931],"iteration":88,"passed_time":0.1889685438,"remaining_time":1.934273522},
{"learn":[5.412331217],"iteration":89,"passed_time":0.1894932947,"remaining_time":1.915987757},
{"learn":[5.400691499],"iteration":90,"passed_time":0.1900258878,"remaining_time":1.898170681},
{"learn":[5.391618744],"iteration":91,"passed_time":0.1905631682,"remaining_time":1.880775616},
{"learn":[5.380766572],"iteration":92,"passed_time":0.1910931072,"remaining_time":1.863671486},
{"learn":[5.372207183],"iteration":93,"passed_time":0.1916212751,"remaining_time":1.846902928},
{"learn":[5.362918837],"iteration":94,"passed_time":0.1921532787,"remaining_time":1.830512813},
{"learn":[5.348292324],"iteration":95,"passed_time":0.1926760159,"remaining_time":1.814365817},
{"learn":[5.339772295],"iteration":96,"passed_time":0.1931821044,"remaining_time":1.798385982},
{"learn":[5.331515983],"iteration":97,"passed_time":0.1939641089,"remaining_time":1.785261492},
{"learn":[5.323861644],"iteration":98,"passed_time":0.1945985506,"remaining_time":1.771043375},
{"learn":[5.313277281],"iteration":99,"passed_time":0.1953118534,"remaining_time":1.757806681},
{"learn":[5.30685627],"iteration":100,"passed_time":0.1961352266,"remaining_time":1.74579771},
{"learn":[5.29652059],"iteration":101,"passed_time":0.196713116,"remaining_time":1.731846845},
{"learn":[5.288350766],"iteration":102,"passed_time":0.1972498536,"remaining_time":1.717797269},
{"learn":[5.27993346],"iteration":103,"passed_time":0.197786826,"remaining_time":1.704009578},
{"learn":[5.271789139],"iteration":104,"passed_time":0.1983123845,"remaining_time":1.690376992},
{"learn":[5.262684686],"iteration":105,"passed_time":0.1988358586,"remaining_time":1.676974128},
{"learn":[5.251619772],"iteration":106,"passed_time":0.199380612,"remaining_time":1.663989593},
{"learn":[5.241012171],"iteration":107,"passed_time":0.1999069633,"remaining_time":1.651083438},
{"learn":[5.232684032],"iteration":108,"passed_time":0.2004246295,"remaining_time":1.638333439},
{"learn":[5.224267141],"iteration":109,"passed_time":0.2009547097,"remaining_time":1.625906287},
{"learn":[5.216324968],"iteration":110,"passed_time":0.2014795313,"remaining_time":1.613651382},
{"learn":[5.211102527],"iteration":111,"passed_time":0.2019933474,"remaining_time":1.601518683},
{"learn":[5.206364257],"iteration":112,"passed_time":0.2025087143,"remaining_time":1.589603801},
{"learn":[5.196937641],"iteration":113,"passed_time":0.2030248106,"remaining_time":1.57789458},
{"learn":[5.190746047],"iteration":114,"passed_time":0.203563951,"remaining_time":1.566557362},
{"learn":[5.181885213],"iteration":115,"passed_time":0.2040945528,"remaining_time":1.555341247},
{"learn":[5.178293568],"iteration":116,"passed_time":0.2045079432,"remaining_time":1.543423196},
{"learn":[5.170991438],"iteration":117,"passed_time":0.205049549,"remaining_time":1.532658493},
{"learn":[5.166257212],"iteration":118,"passed_time":0.2055591796,"remaining_time":1.521828884},
{"learn":[5.161421246],"iteration":119,"passed_time":0.2060718642,"remaining_time":1.511193671},
{"learn":[5.158223542],"iteration":120,"passed_time":0.2065919808,"remaining_time":1.500779761},
{"learn":[5.15470988],"iteration":121,"passed_time":0.207013721,"remaining_time":1.489820058},
{"learn":[5.146388143],"iteration":122,"passed_time":0.2075433301,"remaining_time":1.479800817},
{"learn":[5.139529364],"iteration":123,"passed_time":0.2080666788,"remaining_time":1.469890408},
{"learn":[5.134276023],"iteration":124,"passed_time":0.2085923603,"remaining_time":1.460146522},
{"learn":[5.128536065],"iteration":125,"passed_time":0.20918807,"remaining_time":1.451034708},
{"learn":[5.123300353],"iteration":126,"passed_time":0.2096337663,"remaining_time":1.441025811},
{"learn":[5.116200518],"iteration":127,"passed_time":0.2101965118,"remaining_time":1.431963737},
{"learn":[5.108728704],"iteration":128,"passed_time":0.2107751232,"remaining_time":1.42314056},
{"learn":[5.104075866],"iteration":129,"passed_time":0.2113171641,"remaining_time":1.414199483},
{"learn":[5.100317606],"iteration":130,"passed_time":0.2118431941,"remaining_time":1.405280425},
{"learn":[5.095814182],"iteration":131,"passed_time":0.2123727626,"remaining_time":1.396511803},
{"learn":[5.092146915],"iteration":132,"passed_time":0.2129616642,"remaining_time":1.388253856},
{"learn":[5.085258329],"iteration":133,"passed_time":0.2136702939,"remaining_time":1.380884138},
{"learn":[5.079219421],"iteration":134,"passed_time":0.2144174121,"remaining_time":1.373859714},
{"learn":[5.076476829],"iteration":135,"passed_time":0.2152991997,"remaining_time":1.367783151},
{"learn":[5.072133867],"iteration":136,"passed_time":0.2158707318,"remaining_time":1.359828041},
{"learn":[5.067031564],"iteration":137,"passed_time":0.2164239948,"remaining_time":1.351865823},
{"learn":[5.061358312],"iteration":138,"passed_time":0.2169659951,"remaining_time":1.343940444},
{"learn":[5.056759124],"iteration":139,"passed_time":0.2175068014,"remaining_time":1.336113209},
{"learn":[5.050254],"iteration":140,"passed_time":0.2180575788,"remaining_time":1.328450072},
{"learn":[5.048376474],"iteration":141,"passed_time":0.2184249758,"remaining_time":1.319779079},
{"learn":[5.042603751],"iteration":142,"passed_time":0.2189714584,"remaining_time":1.312297481},
{"learn":[5.037477349],"iteration":143,"passed_time":0.2195241894,"remaining_time":1.304949348},
{"learn":[5.03230489],"iteration":144,"passed_time":0.2200581475,"remaining_time":1.297584249},
{"learn":[5.025976187],"iteration":145,"passed_time":0.22060993,"remaining_time":1.290416988},
{"learn":[5.01952451],"iteration":146,"passed_time":0.2211653151,"remaining_time":1.283360638},
{"learn":[5.017569424],"iteration":147,"passed_time":0.2217134839,"remaining_time":1.276350596},
{"learn":[5.008962367],"iteration":148,"passed_time":0.222248231,"remaining_time":1.269350635},
{"learn":[5.003880266],"iteration":149,"passed_time":0.2227934443,"remaining_time":1.262496184},
{"learn":[4.996387564],"iteration":150,"passed_time":0.2233341331,"remaining_time":1.255699861},
{"learn":[4.993361683],"iteration":151,"passed_time":0.2238735227,"remaining_time":1.248978601},
{"learn":[4.99005752],"iteration":152,"passed_time":0.2245240886,"remaining_time":1.242953615},
{"learn":[4.986908764],"iteration":153,"passed_time":0.2253231985,"remaining_time":1.237814454},
{"learn":[4.985207175],"iteration":154,"passed_time":0.2260288437,"remaining_time":1.232221761},
{"learn":[4.979003494],"iteration":155,"passed_time":0.2266835694,"remaining_time":1.226416234},
{"learn":[4.973142217],"iteration":156,"passed_time":0.2272434128,"remaining_time":1.22016686},
{"learn":[4.967056696],"iteration":157,"passed_time":0.2278121177,"remaining_time":1.214036728},
{"learn":[4.961460696],"iteration":158,"passed_time":0.2283602554,"remaining_time":1.207867766},
{"learn":[4.954240363],"iteration":159,"passed_time":0.2289005989,"remaining_time":1.201728144},
{"learn":[4.952320707],"iteration":160,"passed_time":0.229265991,"remaining_time":1.194746375},
{"learn":[4.948337777],"iteration":161,"passed_time":0.2297784197,"remaining_time":1.188606887},
{"learn":[4.943228639],"iteration":162,"passed_time":0.2302886187,"remaining_time":1.182524993},
{"learn":[4.938545759],"iteration":163,"passed_time":0.2308339885,"remaining_time":1.176690332},
{"learn":[4.935330572],"iteration":164,"passed_time":0.2313675624,"remaining_time":1.170860088},
{"learn":[4.932051543],"iteration":165,"passed_time":0.2318855772,"remaining_time":1.16501549},
{"learn":[4.928964153],"iteration":166,"passed_time":0.2323968869,"remaining_time":1.159201238},
{"learn":[4.922860227],"iteration":167,"passed_time":0.2329269443,"remaining_time":1.153542962},
{"learn":[4.917668772],"iteration":168,"passed_time":0.2334656724,"remaining_time":1.14798801},
{"learn":[4.910365386],"iteration":169,"passed_time":0.234004723,"remaining_time":1.142493648},
{"learn":[4.906457206],"iteration":170,"passed_time":0.2345479069,"remaining_time":1.13707728},
{"learn":[4.901996508],"iteration":171,"passed_time":0.2350710423,"remaining_time":1.131621064},
{"learn":[4.896816173],"iteration":172,"passed_time":0.2356040275,"remaining_time":1.126268964},
{"learn":[4.891123132],"iteration":173,"passed_time":0.2361328256,"remaining_time":1.120952379},
{"learn":[4.887630202],"iteration":174,"passed_time":0.2366552345,"remaining_time":1.115660391},
{"learn":[4.885259712],"iteration":175,"passed_time":0.2372070323,"remaining_time":1.110560197},
{"learn":[4.880659728],"iteration":176,"passed_time":0.2377391452,"remaining_time":1.105419867},
{"learn":[4.877299723],"iteration":177,"passed_time":0.2382613989,"remaining_time":1.100285786},
{"learn":[4.874038772],"iteration":178,"passed_time":0.2387820255,"remaining_time":1.095195771},
{"learn":[4.86943698],"iteration":179,"passed_time":0.2394825442,"remaining_time":1.090976035},
{"learn":[4.861268711],"iteration":180,"passed_time":0.2401999008,"remaining_time":1.086871374},
{"learn":[4.858673056],"iteration":181,"passed_time":0.240803435,"remaining_time":1.082292362},
{"learn":[4.854036207],"iteration":182,"passed_time":0.2415270168,"remaining_time":1.078292747},
{"learn":[4.85130244],"iteration":183,"passed_time":0.2420798671,"remaining_time":1.073571584},
{"learn":[4.847510084],"iteration":184,"passed_time":0.2426153478,"remaining_time":1.068818965},
{"learn":[4.845691673],"iteration":185,"passed_time":0.2431486592,"remaining_time":1.064102197},
{"learn":[4.842058646],"iteration":186,"passed_time":0.2437036692,"remaining_time":1.059524508},
{"learn":[4.838623675],"iteration":187,"passed_time":0.2442386436,"remaining_time":1.054903078},
{"learn":[4.834602161],"iteration":188,"passed_time":0.2447748563,"remaining_time":1.050330204},
{"learn":[4.830858976],"iteration":189,"passed_time":0.2453099587,"remaining_time":1.045795087},
{"learn":[4.827590511],"iteration":190,"passed_time":0.245823032,"remaining_time":1.041208549},
{"learn":[4.822246226],"iteration":191,"passed_time":0.2463580155,"remaining_time":1.036756649},
{"learn":[4.816686395],"iteration":192,"passed_time":0.2468748906,"remaining_time":1.03226962},
{"learn":[4.814797121],"iteration":193,"passed_time":0.2474167435,"remaining_time":1.027927295},
{"learn":[4.811639392],"iteration":194,"passed_time":0.2479375784,"remaining_time":1.023537183},
{"learn":[4.804813432],"iteration":195,"passed_time":0.248466044,"remaining_time":1.019217854},
{"learn":[4.80251613],"iteration":196,"passed_time":0.2489800646,"remaining_time":1.014878131},
{"learn":[4.800087884],"iteration":197,"passed_time":0.2494848667,"remaining_time":1.010539713},
{"learn":[4.794773135],"iteration":198,"passed_time":0.2500028898,"remaining_time":1.006293039},
{"learn":[4.791664833],"iteration":199,"passed_time":0.2505222028,"remaining_time":1.002088811},
{"learn":[4.785989873],"iteration":200,"passed_time":0.2510448369,"remaining_time":0.9979344513},
{"learn":[4.782387142],"iteration":201,"passed_time":0.2515511829,"remaining_time":0.9937517027},
{"learn":[4.778623704],"iteration":202,"passed_time":0.2520667381,"remaining_time":0.9896413315},
{"learn":[4.775772178],"iteration":203,"passed_time":0.2525829028,"remaining_time":0.9855685814},
{"learn":[4.77023101],"iteration":204,"passed_time":0.253096157,"remaining_time":0.9815192431},
{"learn":[4.764496689],"iteration":205,"passed_time":0.253604936,"remaining_time":0.9774869864},
{"learn":[4.763138716],"iteration":206,"passed_time":0.2541809744,"remaining_time":0.9737464382},
{"learn":[4.758053283],"iteration":207,"passed_time":0.2548233465,"remaining_time":0.9702888964},
{"learn":[4.755063788],"iteration":208,"passed_time":0.2554992194,"remaining_time":0.9669850839},
{"learn":[4.752465267],"iteration":209,"passed_time":0.2561409726,"remaining_time":0.9635779445},
{"learn":[4.748067377],"iteration":210,"passed_time":0.2568603122,"remaining_time":0.9604871391},
{"learn":[4.744163298],"iteration":211,"passed_time":0.2574019097,"remaining_time":0.9567580418},
{"learn":[4.736670896],"iteration":212,"passed_time":0.2579486142,"remaining_time":0.9530777436},
{"learn":[4.73349255],"iteration":213,"passed_time":0.258482143,"remaining_time":0.9493783382},
{"learn":[4.731864595],"iteration":214,"passed_time":0.2589910544,"remaining_time":0.9456185011},
{"learn":[4.728398311],"iteration":215,"passed_time":0.2595213048,"remaining_time":0.9419662173},
{"learn":[4.723865975],"iteration":216,"passed_time":0.2600418416,"remaining_time":0.9383076588},
{"learn":[4.723483365],"iteration":217,"passed_time":0.2605327357,"remaining_time":0.9345715564},
{"learn":[4.72095416],"iteration":218,"passed_time":0.2610441568,"remaining_time":0.9309382942},
{"learn":[4.716173382],"iteration":219,"passed_time":0.2615768712,"remaining_time":0.927408907},
{"learn":[4.710563974],"iteration":220,"passed_time":0.2621062128,"remaining_time":0.9238947501},
{"learn":[4.707160263],"iteration":221,"passed_time":0.2626375578,"remaining_time":0.9204145042},
{"learn":[4.70408351],"iteration":222,"passed_time":0.2631702233,"remaining_time":0.9169653073},
{"learn":[4.702501831],"iteration":223,"passed_time":0.2637075674,"remaining_time":0.9135583586},
{"learn":[4.700269738],"iteration":224,"passed_time":0.2642312212,"remaining_time":0.9101297619},
{"learn":[4.695346302],"iteration":225,"passed_time":0.2647621973,"remaining_time":0.90675195},
{"learn":[4.689769299],"iteration":226,"passed_time":0.265286761,"remaining_time":0.9033773844},
{"learn":[4.687919514],"iteration":227,"passed_time":0.2657921689,"remaining_time":0.8999629577},
{"learn":[4.682982074],"iteration":228,"passed_time":0.2663284759,"remaining_time":0.8966779691},
{"learn":[4.679578702],"iteration":229,"passed_time":0.2668561719,"remaining_time":0.8933880538},
{"learn":[4.675751423],"iteration":230,"passed_time":0.2673813914,"remaining_time":0.8901138095},
{"learn":[4.672710726],"iteration":231,"passed_time":0.2679276815,"remaining_time":0.8869330146},
{"learn":[4.6690533],"iteration":232,"passed_time":0.2684539712,"remaining_time":0.8837089952},
{"learn":[4.667595702],"iteration":233,"passed_time":0.2690654755,"remaining_time":0.880786984},
{"learn":[4.664241291],"iteration":234,"passed_time":0.2700457278,"remaining_time":0.8790850287},
{"learn":[4.662246999],"iteration":235,"passed_time":0.2707241264,"remaining_time":0.8764120024},
{"learn":[4.658668443],"iteration":236,"passed_time":0.2714645768,"remaining_time":0.8739555785},
{"learn":[4.658017572],"iteration":237,"passed_time":0.2750077822,"remaining_time":0.880487101},
{"learn":[4.657656705],"iteration":238,"passed_time":0.275791321,"remaining_time":0.8781472606},
{"learn":[4.653242871],"iteration":239,"passed_time":0.2764792067,"remaining_time":0.8755174879},
{"learn":[4.6507302],"iteration":240,"passed_time":0.2770090716,"remaining_time":0.8724061633},
{"learn":[4.647671336],"iteration":241,"passed_time":0.2775388161,"remaining_time":0.8693157958},
{"learn":[4.645506007],"iteration":242,"passed_time":0.2780638112,"remaining_time":0.866231708},
{"learn":[4.641297906],"iteration":243,"passed_time":0.2785953585,"remaining_time":0.8631888978},
{"learn":[4.63798107],"iteration":244,"passed_time":0.2791289378,"remaining_time":0.8601728492},
{"learn":[4.635062318],"iteration":245,"passed_time":0.2796554572,"remaining_time":0.8571553445},
{"learn":[4.631606017],"iteration":246,"passed_time":0.2801860413,"remaining_time":0.8541704011},
{"learn":[4.630215494],"iteration":247,"passed_time":0.2806970827,"remaining_time":0.8511459928},
{"learn":[4.62729814],"iteration":248,"passed_time":0.2812129476,"remaining_time":0.8481563199},
{"learn":[4.624691756],"iteration":249,"passed_time":0.2817435623,"remaining_time":0.8452306868},
{"learn":[4.621840053],"iteration":250,"passed_time":0.282337029,"remaining_time":0.842511692},
{"learn":[4.619602091],"iteration":251,"passed_time":0.283289626,"remaining_time":0.8408755567},
{"learn":[4.613584029],"iteration":252,"passed_time":0.2838501037,"remaining_time":0.838087065},
{"learn":[4.6119388],"iteration":253,"passed_time":0.284381827,"remaining_time":0.8352316651},
{"learn":[4.60870702],"iteration":254,"passed_time":0.2849029302,"remaining_time":0.8323634626},
{"learn":[4.604771557],"iteration":255,"passed_time":0.285631783,"remaining_time":0.8301173692},
{"learn":[4.604231277],"iteration":256,"passed_time":0.2863378045,"remaining_time":0.8278170767},
{"learn":[4.600750354],"iteration":257,"passed_time":0.2870446332,"remaining_time":0.8255314646},
{"learn":[4.596488253],"iteration":258,"passed_time":0.2877684374,"remaining_time":0.8233066105},
{"learn":[4.59470784],"iteration":259,"passed_time":0.2883498569,"remaining_time":0.8206880542},
{"learn":[4.588818005],"iteration":260,"passed_time":0.2889848173,"remaining_time":0.8182367049},
{"learn":[4.585054174],"iteration":261,"passed_time":0.2895603796,"remaining_time":0.8156319089},
{"learn":[4.581471435],"iteration":262,"passed_time":0.2901152911,"remaining_time":0.812984675},
{"learn":[4.577555199],"iteration":263,"passed_time":0.290676843,"remaining_time":0.8103718048},
{"learn":[4.57457145],"iteration":264,"passed_time":0.2911951766,"remaining_time":0.8076545463},
{"learn":[4.573029224],"iteration":265,"passed_time":0.291724329,"remaining_time":0.8049836748},
{"learn":[4.571326203],"iteration":266,"passed_time":0.2922617269,"remaining_time":0.8023514826},
{"learn":[4.571019224],"iteration":267,"passed_time":0.2927717413,"remaining_time":0.7996601292},
{"learn":[4.565766631],"iteration":268,"passed_time":0.293297867,"remaining_time":0.7970287761},
{"learn":[4.563383471],"iteration":269,"passed_time":0.293833166,"remaining_time":0.7944378192},
{"learn":[4.558165805],"iteration":270,"passed_time":0.2943601172,"remaining_time":0.7918395773},
{"learn":[4.55629209],"iteration":271,"passed_time":0.294876707,"remaining_time":0.7892288335},
{"learn":[4.549383848],"iteration":272,"passed_time":0.2954367769,"remaining_time":0.786749219},
{"learn":[4.546227503],"iteration":273,"passed_time":0.2959628641,"remaining_time":0.7841935742},
{"learn":[4.540620977],"iteration":274,"passed_time":0.2965481523,"remaining_time":0.7818087653},
{"learn":[4.532898237],"iteration":275,"passed_time":0.2971153615,"remaining_time":0.7793895715},
{"learn":[4.529757367],"iteration":276,"passed_time":0.2976747061,"remaining_time":0.7769632219},
{"learn":[4.52579294],"iteration":277,"passed_time":0.2982099715,"remaining_time":0.7744877677},
{"learn":[4.521572155],"iteration":278,"passed_time":0.2987516758,"remaining_time":0.7720428611},
{"learn":[4.518818099],"iteration":279,"passed_time":0.2992926018,"remaining_time":0.7696095474},
{"learn":[4.514012334],"iteration":280,"passed_time":0.2998373431,"remaining_time":0.7671994651},
{"learn":[4.508331416],"iteration":281,"passed_time":0.3005030959,"remaining_time":0.7651107194},
{"learn":[4.506038537],"iteration":282,"passed_time":0.3010752345,"remaining_time":0.762794852},
{"learn":[4.505805643],"iteration":283,"passed_time":0.3016033238,"remaining_time":0.7603802107},
{"learn":[4.501550352],"iteration":284,"passed_time":0.3021826754,"remaining_time":0.7581074136},
{"learn":[4.494692643],"iteration":285,"passed_time":0.302738296,"remaining_time":0.7557872146},
{"learn":[4.489330245],"iteration":286,"passed_time":0.3032765977,"remaining_time":0.7534362863},
{"learn":[4.484826955],"iteration":287,"passed_time":0.3038488622,"remaining_time":0.7511819092},
{"learn":[4.478285428],"iteration":288,"passed_time":0.3044203168,"remaining_time":0.7489371808},
{"learn":[4.475311671],"iteration":289,"passed_time":0.3049908797,"remaining_time":0.746701809},
{"learn":[4.471581298],"iteration":290,"passed_time":0.3056077375,"remaining_time":0.744590673},
{"learn":[4.469164956],"iteration":291,"passed_time":0.3061952969,"remaining_time":0.7424187335},
{"learn":[4.462068024],"iteration":292,"passed_time":0.3069319609,"remaining_time":0.7406173937},
{"learn":[4.458540976],"iteration":293,"passed_time":0.3074799674,"remaining_time":0.7383702619},
{"learn":[4.455757458],"iteration":294,"passed_time":0.3080059474,"remaining_time":0.7360820099},
{"learn":[4.453027414],"iteration":295,"passed_time":0.3085448759,"remaining_time":0.7338364615},
{"learn":[4.450659338],"iteration":296,"passed_time":0.309076516,"remaining_time":0.731585154},
{"learn":[4.444696901],"iteration":297,"passed_time":0.3096071447,"remaining_time":0.7293430053},
{"learn":[4.442052813],"iteration":298,"passed_time":0.3101370808,"remaining_time":0.7271106811},
{"learn":[4.440036756],"iteration":299,"passed_time":0.3107303297,"remaining_time":0.7250374361},
{"learn":[4.435017051],"iteration":300,"passed_time":0.3114649938,"remaining_time":0.7233024274},
{"learn":[4.429962125],"iteration":301,"passed_time":0.3120220092,"remaining_time":0.7211634517},
{"learn":[4.427666256],"iteration":302,"passed_time":0.3125450974,"remaining_time":0.7189568743},
{"learn":[4.425030004],"iteration":303,"passed_time":0.3130921617,"remaining_time":0.7168162649},
{"learn":[4.422588771],"iteration":304,"passed_time":0.3136070777,"remaining_time":0.7146128493},
{"learn":[4.418936667],"iteration":305,"passed_time":0.3141155649,"remaining_time":0.7124058889},
{"learn":[4.416887976],"iteration":306,"passed_time":0.3146296214,"remaining_time":0.7102225657},
{"learn":[4.413773354],"iteration":307,"passed_time":0.3151642543,"remaining_time":0.7080963116},
{"learn":[4.411129391],"iteration":308,"passed_time":0.3158034229,"remaining_time":0.706214127},
{"learn":[4.40850819],"iteration":309,"passed_time":0.3166109937,"remaining_time":0.7047147923},
{"learn":[4.404880292],"iteration":310,"passed_time":0.3173072532,"remaining_time":0.7029733037},
{"learn":[4.404593827],"iteration":311,"passed_time":0.3179434601,"remaining_time":0.7011060915},
{"learn":[4.402139942],"iteration":312,"passed_time":0.3186417462,"remaining_time":0.6993830019},
{"learn":[4.400284725],"iteration":313,"passed_time":0.3194529521,"remaining_time":0.6979131375},
{"learn":[4.395805521],"iteration":314,"passed_time":0.3203304554,"remaining_time":0.6965916253},
{"learn":[4.392838833],"iteration":315,"passed_time":0.3208530071,"remaining_time":0.6945046104},
{"learn":[4.389213061],"iteration":316,"passed_time":0.3213807201,"remaining_time":0.6924385862},
{"learn":[4.3861981],"iteration":317,"passed_time":0.3219425449,"remaining_time":0.690455395},
{"learn":[4.385054234],"iteration":318,"passed_time":0.3224681146,"remaining_time":0.688403718},
{"learn":[4.379364607],"iteration":319,"passed_time":0.3229874662,"remaining_time":0.6863483656},
{"learn":[4.378387619],"iteration":320,"passed_time":0.3235042402,"remaining_time":0.6842971311},
{"learn":[4.375816727],"iteration":321,"passed_time":0.3240362202,"remaining_time":0.682287445},
{"learn":[4.374600202],"iteration":322,"passed_time":0.324545202,"remaining_time":0.6802387052},
{"learn":[4.37098897],"iteration":323,"passed_time":0.3250665085,"remaining_time":0.6782251843},
{"learn":[4.367418484],"iteration":324,"passed_time":0.325608067,"remaining_time":0.6762629085},
{"learn":[4.363584638],"iteration":325,"passed_time":0.3261254919,"remaining_time":0.6742594525},
{"learn":[4.360770706],"iteration":326,"passed_time":0.3266465073,"remaining_time":0.6722724752},
{"learn":[4.358675808],"iteration":327,"passed_time":0.3273898999,"remaining_time":0.6707500389},
{"learn":[4.354228195],"iteration":328,"passed_time":0.3281133042,"remaining_time":0.6691915717},
{"learn":[4.353773425],"iteration":329,"passed_time":0.3287101975,"remaining_time":0.66738131},
{"learn":[4.351648009],"iteration":330,"passed_time":0.329250796,"remaining_time":0.6654645997},
{"learn":[4.348209927],"iteration":331,"passed_time":0.3298715792,"remaining_time":0.6637175147},
{"learn":[4.345852733],"iteration":332,"passed_time":0.3304978407,"remaining_time":0.6619881675},
{"learn":[4.34237339],"iteration":333,"passed_time":0.3312362497,"remaining_time":0.6604890489},
{"learn":[4.340814362],"iteration":334,"passed_time":0.3318089969,"remaining_time":0.6586656207},
{"learn":[4.339707068],"iteration":335,"passed_time":0.332571516,"remaining_time":0.6572246627},
{"learn":[4.335430786],"iteration":336,"passed_time":0.3333629928,"remaining_time":0.6558447009},
{"learn":[4.33521887],"iteration":337,"passed_time":0.3338909318,"remaining_time":0.6539520617},
{"learn":[4.328507238],"iteration":338,"passed_time":0.3344979625,"remaining_time":0.652221691},
{"learn":[4.326140732],"iteration":339,"passed_time":0.3351363905,"remaining_time":0.6505588758},
{"learn":[4.323785636],"iteration":340,"passed_time":0.3356535798,"remaining_time":0.6486677686},
{"learn":[4.320632534],"iteration":341,"passed_time":0.3361696459,"remaining_time":0.6467825351},
{"learn":[4.31973724],"iteration":342,"passed_time":0.3366790409,"remaining_time":0.644892507},
{"learn":[4.318000924],"iteration":343,"passed_time":0.337189863,"remaining_time":0.6430132271},
{"learn":[4.312713628],"iteration":344,"passed_time":0.3377170361,"remaining_time":0.6411729236},
{"learn":[4.308220789],"iteration":345,"passed_time":0.3382530575,"remaining_time":0.6393569353},
{"learn":[4.305890947],"iteration":346,"passed_time":0.3387831418,"remaining_time":0.6375371516},
{"learn":[4.305137856],"iteration":347,"passed_time":0.3395941483,"remaining_time":0.6362511054},
{"learn":[4.304787172],"iteration":348,"passed_time":0.3401641151,"remaining_time":0.634518163},
{"learn":[4.30350134],"iteration":349,"passed_time":0.340822743,"remaining_time":0.6329565228},
{"learn":[4.30293809],"iteration":350,"passed_time":0.3413351954,"remaining_time":0.6311297487},
{"learn":[4.299548459],"iteration":351,"passed_time":0.3418590951,"remaining_time":0.6293315159},
{"learn":[4.294768408],"iteration":352,"passed_time":0.3423834787,"remaining_time":0.6275413902},
{"learn":[4.294581479],"iteration":353,"passed_time":0.3428834078,"remaining_time":0.6257137893},
{"learn":[4.292551604],"iteration":354,"passed_time":0.3433984169,"remaining_time":0.6239210674},
{"learn":[4.288628894],"iteration":355,"passed_time":0.3439237433,"remaining_time":0.6221541872},
{"learn":[4.287802767],"iteration":356,"passed_time":0.3444787988,"remaining_time":0.6204478085},
{"learn":[4.284566905],"iteration":357,"passed_time":0.3450377169,"remaining_time":0.6187547885},
{"learn":[4.27890232],"iteration":358,"passed_time":0.3456748392,"remaining_time":0.6172077213},
{"learn":[4.276938023],"iteration":359,"passed_time":0.3462719399,"remaining_time":0.6155945599},
{"learn":[4.273425094],"iteration":360,"passed_time":0.3470020852,"remaining_time":0.6142225276},
{"learn":[4.269726505],"iteration":361,"passed_time":0.3476420429,"remaining_time":0.6126950922},
{"learn":[4.265565857],"iteration":362,"passed_time":0.3481909598,"remaining_time":0.6110127862},
{"learn":[4.262117173],"iteration":363,"passed_time":0.3488206496,"remaining_time":0.6094778384},
{"learn":[4.259185148],"iteration":364,"passed_time":0.3495080071,"remaining_time":0.6080481767},
{"learn":[4.257668507],"iteration":365,"passed_time":0.3500478993,"remaining_time":0.6063671262},
{"learn":[4.253432436],"iteration":366,"passed_time":0.3505811006,"remaining_time":0.6046807539},
{"learn":[4.250216667],"iteration":367,"passed_time":0.35110472,"remaining_time":0.6029841931},
{"learn":[4.24514828],"iteration":368,"passed_time":0.3517508326,"remaining_time":0.6015034562},
{"learn":[4.244015772],"iteration":369,"passed_time":0.3523250216,"remaining_time":0.5999047666},
{"learn":[4.240329192],"iteration":370,"passed_time":0.3529541783,"remaining_time":0.5984047928},
{"learn":[4.236718014],"iteration":371,"passed_time":0.3535549855,"remaining_time":0.5968616421},
{"learn":[4.233495944],"iteration":372,"passed_time":0.3540900245,"remaining_time":0.5952129902},
{"learn":[4.230357491],"iteration":373,"passed_time":0.3546370796,"remaining_time":0.593590406},
{"learn":[4.227381215],"iteration":374,"passed_time":0.355156829,"remaining_time":0.5919280484},
{"learn":[4.226169067],"iteration":375,"passed_time":0.355672867,"remaining_time":0.590265609},
{"learn":[4.225963861],"iteration":376,"passed_time":0.3561697159,"remaining_time":0.5885775412},
{"learn":[4.224346548],"iteration":377,"passed_time":0.3566891942,"remaining_time":0.5869330126},
{"learn":[4.222595381],"iteration":378,"passed_time":0.3572081644,"remaining_time":0.5852935887},
{"learn":[4.219700938],"iteration":379,"passed_time":0.3578103486,"remaining_time":0.5837958319},
{"learn":[4.216356207],"iteration":380,"passed_time":0.3584481783,"remaining_time":0.5823606887},
{"learn":[4.214326494],"iteration":381,"passed_time":0.3591544871,"remaining_time":0.5810405054},
{"learn":[4.212901398],"iteration":382,"passed_time":0.3596839501,"remaining_time":0.579438635},
{"learn":[4.211331091],"iteration":383,"passed_time":0.360217962,"remaining_time":0.5778496473},
{"learn":[4.208624791],"iteration":384,"passed_time":0.3607403899,"remaining_time":0.5762476358},
{"learn":[4.204659106],"iteration":385,"passed_time":0.3613564515,"remaining_time":0.5748001586},
{"learn":[4.202968852],"iteration":386,"passed_time":0.3620093817,"remaining_time":0.5734153772},
{"learn":[4.197261935],"iteration":387,"passed_time":0.3626216072,"remaining_time":0.571970164},
{"learn":[4.196934403],"iteration":388,"passed_time":0.363137622,"remaining_time":0.5703781158},
{"learn":[4.192479929],"iteration":389,"passed_time":0.3636823298,"remaining_time":0.5688364645},
{"learn":[4.190243116],"iteration":390,"passed_time":0.3642915646,"remaining_time":0.5674004165},
{"learn":[4.185852431],"iteration":391,"passed_time":0.3648520729,"remaining_time":0.5658930111},
{"learn":[4.180967944],"iteration":392,"passed_time":0.3654247576,"remaining_time":0.5644092311},
{"learn":[4.178283162],"iteration":393,"passed_time":0.365949927,"remaining_time":0.5628569943},
{"learn":[4.176341157],"iteration":394,"passed_time":0.3665265727,"remaining_time":0.5613888012},
{"learn":[4.176041504],"iteration":395,"passed_time":0.367021398,"remaining_time":0.5598003142},
{"learn":[4.175564513],"iteration":396,"passed_time":0.3675380052,"remaining_time":0.558250421},
{"learn":[4.170830274],"iteration":397,"passed_time":0.3680669461,"remaining_time":0.5567243758},
{"learn":[4.167804808],"iteration":398,"passed_time":0.3685905858,"remaining_time":0.5551953435},
{"learn":[4.165860548],"iteration":399,"passed_time":0.3691075494,"remaining_time":0.5536613242},
{"learn":[4.160950571],"iteration":400,"passed_time":0.3696344398,"remaining_time":0.5521472056},
{"learn":[4.158544115],"iteration":401,"passed_time":0.3701433285,"remaining_time":0.55061122},
{"learn":[4.154448767],"iteration":402,"passed_time":0.3707510618,"remaining_time":0.5492267591},
{"learn":[4.15197457],"iteration":403,"passed_time":0.3712968945,"remaining_time":0.5477548245},
{"learn":[4.149562679],"iteration":404,"passed_time":0.3720615378,"remaining_time":0.5466089259},
{"learn":[4.149327961],"iteration":405,"passed_time":0.3725896465,"remaining_time":0.5451188425},
{"learn":[4.147444889],"iteration":406,"passed_time":0.3731142119,"remaining_time":0.5436283235},
{"learn":[4.147254809],"iteration":407,"passed_time":0.3736075978,"remaining_time":0.5420972988},
{"learn":[4.144589165],"iteration":408,"passed_time":0.3741288322,"remaining_time":0.5406115889},
{"learn":[4.141691034],"iteration":409,"passed_time":0.3746515529,"remaining_time":0.5391327224},
{"learn":[4.138893468],"iteration":410,"passed_time":0.3751711996,"remaining_time":0.5376541035},
{"learn":[4.136964597],"iteration":411,"passed_time":0.3757643492,"remaining_time":0.536285042},
{"learn":[4.133773523],"iteration":412,"passed_time":0.3764028571,"remaining_time":0.534984206},
{"learn":[4.131363444],"iteration":413,"passed_time":0.3771703557,"remaining_time":0.5338691508},
{"learn":[4.130228592],"iteration":414,"passed_time":0.3778083846,"remaining_time":0.5325732651},
{"learn":[4.12884186],"iteration":415,"passed_time":0.3790453101,"remaining_time":0.5321213008},
{"learn":[4.12413494],"iteration":416,"passed_time":0.3797533577,"remaining_time":0.5309261572},
{"learn":[4.119422508],"iteration":417,"passed_time":0.3802886787,"remaining_time":0.5294928492},
{"learn":[4.117038244],"iteration":418,"passed_time":0.3808077516,"remaining_time":0.5280412975},
{"learn":[4.116067631],"iteration":419,"passed_time":0.3813190692,"remaining_time":0.5265834765},
{"learn":[4.110343455],"iteration":420,"passed_time":0.3818365934,"remaining_time":0.5251386878},
{"learn":[4.105604544],"iteration":421,"passed_time":0.3823585821,"remaining_time":0.5237044086},
{"learn":[4.103390131],"iteration":422,"passed_time":0.3828944776,"remaining_time":0.5222934127},
{"learn":[4.096724402],"iteration":423,"passed_time":0.3837158562,"remaining_time":0.5212743707},
{"learn":[4.093431279],"iteration":424,"passed_time":0.384443807,"remaining_time":0.5201298565},
{"learn":[4.091412744],"iteration":425,"passed_time":0.3851038508,"remaining_time":0.5188957989},
{"learn":[4.091192901],"iteration":426,"passed_time":0.3856094073,"remaining_time":0.5174571203},
{"learn":[4.088994581],"iteration":427,"passed_time":0.386143473,"remaining_time":0.5160609031},
{"learn":[4.087845355],"iteration":428,"passed_time":0.3866938649,"remaining_time":0.5146904356},
{"learn":[4.083650279],"iteration":429,"passed_time":0.3872180751,"remaining_time":0.5132890763},
{"learn":[4.079840652],"iteration":430,"passed_time":0.3877399665,"remaining_time":0.511888726},
{"learn":[4.075707828],"iteration":431,"passed_time":0.3882591326,"remaining_time":0.5104888595},
{"learn":[4.071345409],"iteration":432,"passed_time":0.3887826534,"remaining_time":0.5090987633},
{"learn":[4.067460475],"iteration":433,"passed_time":0.3893046794,"remaining_time":0.5077107109},
{"learn":[4.064914749],"iteration":434,"passed_time":0.3899566971,"remaining_time":0.5064954802},
{"learn":[4.063823175],"iteration":435,"passed_time":0.3907701134,"remaining_time":0.5054916146},
{"learn":[4.058898471],"iteration":436,"passed_time":0.391499174,"remaining_time":0.5043799428},
{"learn":[4.054120355],"iteration":437,"passed_time":0.3921900724,"remaining_time":0.5032210518},
{"learn":[4.052715901],"iteration":438,"passed_time":0.3927953557,"remaining_time":0.501954885},
{"learn":[4.052114167],"iteration":439,"passed_time":0.393552805,"remaining_time":0.5008853882},
{"learn":[4.051377267],"iteration":440,"passed_time":0.3941148335,"remaining_time":0.4995695962},
{"learn":[4.049275336],"iteration":441,"passed_time":0.3946339764,"remaining_time":0.4982030743},
{"learn":[4.047099198],"iteration":442,"passed_time":0.3951499423,"remaining_time":0.4968363835},
{"learn":[4.044348685],"iteration":443,"passed_time":0.3957262999,"remaining_time":0.4955491503},
{"learn":[4.042822379],"iteration":444,"passed_time":0.3962748223,"remaining_time":0.4942303963},
{"learn":[4.041258611],"iteration":445,"passed_time":0.3970046653,"remaining_time":0.4931403242},
{"learn":[4.040044254],"iteration":446,"passed_time":0.397657321,"remaining_time":0.4919563726},
{"learn":[4.036860137],"iteration":447,"passed_time":0.3981922271,"remaining_time":0.4906297084},
{"learn":[4.036372284],"iteration":448,"passed_time":0.3987065296,"remaining_time":0.4892812869},
{"learn":[4.03368231],"iteration":449,"passed_time":0.3992178042,"remaining_time":0.4879328718},
{"learn":[4.032439519],"iteration":450,"passed_time":0.3997231992,"remaining_time":0.4865810119},
{"learn":[4.032008634],"iteration":451,"passed_time":0.4002188434,"remaining_time":0.4852210757},
{"learn":[4.030034932],"iteration":452,"passed_time":0.4007289509,"remaining_time":0.4838824198},
{"learn":[4.028173412],"iteration":453,"passed_time":0.4012313432,"remaining_time":0.4825381353},
{"learn":[4.023806097],"iteration":454,"passed_time":0.401833799,"remaining_time":0.4813174076},
{"learn":[4.020239186],"iteration":455,"passed_time":0.4024977828,"remaining_time":0.4801727935},
{"learn":[4.017384838],"iteration":456,"passed_time":0.4033628799,"remaining_time":0.4792692424},
{"learn":[4.016468229],"iteration":457,"passed_time":0.403918691,"remaining_time":0.4779998483},
{"learn":[4.014530169],"iteration":458,"passed_time":0.4044408821,"remaining_time":0.4766939373},
{"learn":[4.012884822],"iteration":459,"passed_time":0.4049672488,"remaining_time":0.4753963356},
{"learn":[4.008924707],"iteration":460,"passed_time":0.4056155845,"remaining_time":0.4742446856},
{"learn":[4.008286778],"iteration":461,"passed_time":0.4061375827,"remaining_time":0.4729480941},
{"learn":[4.006444202],"iteration":462,"passed_time":0.4067178368,"remaining_time":0.4717224155},
{"learn":[4.003284363],"iteration":463,"passed_time":0.4073120718,"remaining_time":0.4705156692},
{"learn":[3.999811484],"iteration":464,"passed_time":0.4078861802,"remaining_time":0.4692884009},
{"learn":[3.997483319],"iteration":465,"passed_time":0.4086137343,"remaining_time":0.4682397728},
{"learn":[3.99708333],"iteration":466,"passed_time":0.4092570338,"remaining_time":0.4670963576},
{"learn":[3.995860263],"iteration":467,"passed_time":0.4100604766,"remaining_time":0.4661371229},
{"learn":[3.994131111],"iteration":468,"passed_time":0.4107377756,"remaining_time":0.4650357332},
{"learn":[3.993125499],"iteration":469,"passed_time":0.4114424984,"remaining_time":0.4639670727},
{"learn":[3.992954084],"iteration":470,"passed_time":0.4120818376,"remaining_time":0.4628265225},
{"learn":[3.990635743],"iteration":471,"passed_time":0.4127842623,"remaining_time":0.4617586664},
{"learn":[3.986678254],"iteration":472,"passed_time":0.4133356942,"remaining_time":0.4605241244},
{"learn":[3.986393291],"iteration":473,"passed_time":0.4138289195,"remaining_time":0.4592278727},
{"learn":[3.986152671],"iteration":474,"passed_time":0.4145353927,"remaining_time":0.4581706972},
{"learn":[3.985596662],"iteration":475,"passed_time":0.4151247707,"remaining_time":0.4569860922},
{"learn":[3.983853457],"iteration":476,"passed_time":0.4156757187,"remaining_time":0.4557618467},
{"learn":[3.983263928],"iteration":477,"passed_time":0.4162193476,"remaining_time":0.4545324256},
{"learn":[3.980067202],"iteration":478,"passed_time":0.4167424918,"remaining_time":0.4532835871},
{"learn":[3.978115407],"iteration":479,"passed_time":0.4172626506,"remaining_time":0.4520345382},
{"learn":[3.972661644],"iteration":480,"passed_time":0.4177797347,"remaining_time":0.4507852023},
{"learn":[3.969938254],"iteration":481,"passed_time":0.4183108371,"remaining_time":0.4495539701},
{"learn":[3.968211434],"iteration":482,"passed_time":0.4188428075,"remaining_time":0.4483265662},
{"learn":[3.966113368],"iteration":483,"passed_time":0.4193722365,"remaining_time":0.4470993265},
{"learn":[3.962246044],"iteration":484,"passed_time":0.4199049795,"remaining_time":0.4458784834},
{"learn":[3.961319703],"iteration":485,"passed_time":0.4205325249,"remaining_time":0.4447607362},
{"learn":[3.96078191],"iteration":486,"passed_time":0.4210840346,"remaining_time":0.4435649071},
{"learn":[3.958913633],"iteration":487,"passed_time":0.4216850152,"remaining_time":0.4424236225},
{"learn":[3.957428286],"iteration":488,"passed_time":0.4223539355,"remaining_time":0.441355544},
{"learn":[3.952641965],"iteration":489,"passed_time":0.423214333,"remaining_time":0.4404883874},
{"learn":[3.951486786],"iteration":490,"passed_time":0.4238852727,"remaining_time":0.439424855},
{"learn":[3.94938344],"iteration":491,"passed_time":0.4245599665,"remaining_time":0.4383667947},
{"learn":[3.947297924],"iteration":492,"passed_time":0.4251479788,"remaining_time":0.4372211466},
{"learn":[3.946284886],"iteration":493,"passed_time":0.425700923,"remaining_time":0.4360418361},
{"learn":[3.943288204],"iteration":494,"passed_time":0.4262572756,"remaining_time":0.4348685337},
{"learn":[3.943076488],"iteration":495,"passed_time":0.4277891465,"remaining_time":0.4346889714},
{"learn":[3.942347078],"iteration":496,"passed_time":0.4283920596,"remaining_time":0.4335637948},
{"learn":[3.940251541],"iteration":497,"passed_time":0.4289147277,"remaining_time":0.4323598259},
{"learn":[3.939011019],"iteration":498,"passed_time":0.4294310157,"remaining_time":0.4311521821},
{"learn":[3.938760512],"iteration":499,"passed_time":0.4299365453,"remaining_time":0.4299365453},
{"learn":[3.934522727],"iteration":500,"passed_time":0.4304696633,"remaining_time":0.4287512216},
{"learn":[3.930091193],"iteration":501,"passed_time":0.4310173502,"remaining_time":0.427582949},
{"learn":[3.927671752],"iteration":502,"passed_time":0.4315327651,"remaining_time":0.426385257},
{"learn":[3.927280041],"iteration":503,"passed_time":0.4320569728,"remaining_time":0.4251989256},
{"learn":[3.925987561],"iteration":504,"passed_time":0.4331545511,"remaining_time":0.4245772333},
{"learn":[3.921645957],"iteration":505,"passed_time":0.4343849832,"remaining_time":0.424083363},
{"learn":[3.920333743],"iteration":506,"passed_time":0.4349081315,"remaining_time":0.422898834},
{"learn":[3.918659461],"iteration":507,"passed_time":0.4354273878,"remaining_time":0.4217131394},
{"learn":[3.916124385],"iteration":508,"passed_time":0.4360072511,"remaining_time":0.4205885271},
{"learn":[3.913849268],"iteration":509,"passed_time":0.4367298629,"remaining_time":0.4196032017},
{"learn":[3.912826119],"iteration":510,"passed_time":0.4374402421,"remaining_time":0.4186071984},
{"learn":[3.910034145],"iteration":511,"passed_time":0.4380145264,"remaining_time":0.4174825955},
{"learn":[3.90792379],"iteration":512,"passed_time":0.4386774972,"remaining_time":0.4164443297},
{"learn":[3.907823851],"iteration":513,"passed_time":0.4392261562,"remaining_time":0.4152994395},
{"learn":[3.904527401],"iteration":514,"passed_time":0.4397758662,"remaining_time":0.4141578546},
{"learn":[3.903378283],"iteration":515,"passed_time":0.4404312353,"remaining_time":0.4131176703},
{"learn":[3.902170135],"iteration":516,"passed_time":0.4409906415,"remaining_time":0.4119893227},
{"learn":[3.899435429],"iteration":517,"passed_time":0.4415215973,"remaining_time":0.4108366986},
{"learn":[3.897497505],"iteration":518,"passed_time":0.4420322516,"remaining_time":0.4096676552},
{"learn":[3.896426119],"iteration":519,"passed_time":0.442538261,"remaining_time":0.4084968563},
{"learn":[3.896044669],"iteration":520,"passed_time":0.4430390794,"remaining_time":0.4073238369},
{"learn":[3.892795942],"iteration":521,"passed_time":0.4435861217,"remaining_time":0.4061957206},
{"learn":[3.892413888],"iteration":522,"passed_time":0.4440892343,"remaining_time":0.4050297606},
{"learn":[3.891738985],"iteration":523,"passed_time":0.4445973033,"remaining_time":0.4038708328},
{"learn":[3.88822057],"iteration":524,"passed_time":0.4457371566,"remaining_time":0.4032859988},
{"learn":[3.883837053],"iteration":525,"passed_time":0.4462826241,"remaining_time":0.4021634293},
{"learn":[3.881769742],"iteration":526,"passed_time":0.4470096218,"remaining_time":0.4012059793},
{"learn":[3.880356898],"iteration":527,"passed_time":0.4475791596,"remaining_time":0.4001086427},
{"learn":[3.879250273],"iteration":528,"passed_time":0.4480997942,"remaining_time":0.39896976},
{"learn":[3.877174493],"iteration":529,"passed_time":0.4486263852,"remaining_time":0.3978384925},
{"learn":[3.875854201],"iteration":530,"passed_time":0.4491555501,"remaining_time":0.3967117758},
{"learn":[3.873189396],"iteration":531,"passed_time":0.4496781912,"remaining_time":0.3955815667},
{"learn":[3.871583368],"iteration":532,"passed_time":0.4501903215,"remaining_time":0.394444428},
{"learn":[3.869622679],"iteration":533,"passed_time":0.4507061971,"remaining_time":0.3933128986},
{"learn":[3.866860164],"iteration":534,"passed_time":0.4512190196,"remaining_time":0.392181017},
{"learn":[3.864498444],"iteration":535,"passed_time":0.4518644876,"remaining_time":0.3911662728},
{"learn":[3.861416322],"iteration":536,"passed_time":0.4525919411,"remaining_time":0.3902235916},
{"learn":[3.860265769],"iteration":537,"passed_time":0.4533914352,"remaining_time":0.3893435745},
{"learn":[3.859328725],"iteration":538,"passed_time":0.4542287145,"remaining_time":0.3884961732},
{"learn":[3.858521278],"iteration":539,"passed_time":0.4547755527,"remaining_time":0.3874013967},
{"learn":[3.85599111],"iteration":540,"passed_time":0.4553041942,"remaining_time":0.3862932073},
{"learn":[3.852379816],"iteration":541,"passed_time":0.4558424094,"remaining_time":0.3851952463},
{"learn":[3.851327537],"iteration":542,"passed_time":0.4563758723,"remaining_time":0.3840953474},
{"learn":[3.847854898],"iteration":543,"passed_time":0.4569108256,"remaining_time":0.3829987803},
{"learn":[3.847083414],"iteration":544,"passed_time":0.4574230826,"remaining_time":0.3818853258},
{"learn":[3.845397429],"iteration":545,"passed_time":0.4580040595,"remaining_time":0.3808312143},
{"learn":[3.841933528],"iteration":546,"passed_time":0.4586396421,"remaining_time":0.3798240546},
{"learn":[3.840996474],"iteration":547,"passed_time":0.4592659674,"remaining_time":0.3788106155},
{"learn":[3.838355966],"iteration":548,"passed_time":0.4598157007,"remaining_time":0.3777356667},
{"learn":[3.83342799],"iteration":549,"passed_time":0.460344726,"remaining_time":0.3766456849},
{"learn":[3.828161535],"iteration":550,"passed_time":0.4608717021,"remaining_time":0.3755560694},
{"learn":[3.823502399],"iteration":551,"passed_time":0.4614281516,"remaining_time":0.3744924129},
{"learn":[3.820068862],"iteration":552,"passed_time":0.4619659714,"remaining_time":0.373415532},
{"learn":[3.817951642],"iteration":553,"passed_time":0.4624653428,"remaining_time":0.3723096442},
{"learn":[3.815785958],"iteration":554,"passed_time":0.4629682803,"remaining_time":0.3712088014},
{"learn":[3.81503012],"iteration":555,"passed_time":0.4634884504,"remaining_time":0.3701238704},
{"learn":[3.813529315],"iteration":556,"passed_time":0.4642962956,"remaining_time":0.3692697647},
{"learn":[3.808881326],"iteration":557,"passed_time":0.4651464442,"remaining_time":0.368449334},
{"learn":[3.808740434],"iteration":558,"passed_time":0.4657717085,"remaining_time":0.3674513836},
{"learn":[3.80714352],"iteration":559,"passed_time":0.4663399274,"remaining_time":0.3664099429},
{"learn":[3.80573346],"iteration":560,"passed_time":0.4671998898,"remaining_time":0.3655984877},
{"learn":[3.803370052],"iteration":561,"passed_time":0.4680126652,"remaining_time":0.3647500843},
{"learn":[3.803215211],"iteration":562,"passed_time":0.4687098508,"remaining_time":0.3638120867},
{"learn":[3.801309667],"iteration":563,"passed_time":0.4694054211,"remaining_time":0.3628736943},
{"learn":[3.800003847],"iteration":564,"passed_time":0.4699942593,"remaining_time":0.3618539873},
{"learn":[3.798026138],"iteration":565,"passed_time":0.4709436926,"remaining_time":0.3611123014},
{"learn":[3.794745847],"iteration":566,"passed_time":0.4717075424,"remaining_time":0.3602281585},
{"learn":[3.794312041],"iteration":567,"passed_time":0.4722772732,"remaining_time":0.3591967993},
{"learn":[3.792205926],"iteration":568,"passed_time":0.4728846658,"remaining_time":0.3581955904},
{"learn":[3.788991061],"iteration":569,"passed_time":0.4735105092,"remaining_time":0.3572096824},
{"learn":[3.787391572],"iteration":570,"passed_time":0.4740473259,"remaining_time":0.3561581485},
{"learn":[3.7826445],"iteration":571,"passed_time":0.4745925168,"remaining_time":0.3551146804},
{"learn":[3.781700331],"iteration":572,"passed_time":0.4751046984,"remaining_time":0.3540483529},
{"learn":[3.780045374],"iteration":573,"passed_time":0.4756250862,"remaining_time":0.3529900465},
{"learn":[3.775462644],"iteration":574,"passed_time":0.4761553117,"remaining_time":0.3519408826},
{"learn":[3.773711943],"iteration":575,"passed_time":0.4766878825,"remaining_time":0.3508952468},
{"learn":[3.772415806],"iteration":576,"passed_time":0.4773271066,"remaining_time":0.3499295773},
{"learn":[3.770170875],"iteration":577,"passed_time":0.4780478588,"remaining_time":0.3490245612},
{"learn":[3.765166479],"iteration":578,"passed_time":0.4785931151,"remaining_time":0.3479925759},
{"learn":[3.763976102],"iteration":579,"passed_time":0.4791431614,"remaining_time":0.3469657375},
{"learn":[3.760761708],"iteration":580,"passed_time":0.4796542558,"remaining_time":0.3459124496},
{"learn":[3.758155662],"iteration":581,"passed_time":0.4801855854,"remaining_time":0.3448755579},
{"learn":[3.756844548],"iteration":582,"passed_time":0.4807103384,"remaining_time":0.3438356966},
{"learn":[3.753098923],"iteration":583,"passed_time":0.4812309696,"remaining_time":0.3427946633},
{"learn":[3.751618946],"iteration":584,"passed_time":0.4817432439,"remaining_time":0.3417494807},
{"learn":[3.751398464],"iteration":585,"passed_time":0.4822982755,"remaining_time":0.3407363243},
{"learn":[3.749920103],"iteration":586,"passed_time":0.4829872479,"remaining_time":0.3398189666},
{"learn":[3.748237465],"iteration":587,"passed_time":0.4836090222,"remaining_time":0.3388553013},
{"learn":[3.746021536],"iteration":588,"passed_time":0.4841460119,"remaining_time":0.3378336348},
{"learn":[3.74417648],"iteration":589,"passed_time":0.4847802213,"remaining_time":0.3368811708},
{"learn":[3.738788389],"iteration":590,"passed_time":0.4855721009,"remaining_time":0.3360388989},
{"learn":[3.736021611],"iteration":591,"passed_time":0.4861240652,"remaining_time":0.3350314503},
{"learn":[3.734546151],"iteration":592,"passed_time":0.4866873153,"remaining_time":0.3340332839},
{"learn":[3.733527479],"iteration":593,"passed_time":0.4871959647,"remaining_time":0.3329992621},
{"learn":[3.733026392],"iteration":594,"passed_time":0.4876964879,"remaining_time":0.3319614749},
{"learn":[3.730314752],"iteration":595,"passed_time":0.488236198,"remaining_time":0.3309520536},
{"learn":[3.727342596],"iteration":596,"passed_time":0.4888635463,"remaining_time":0.3300033654},
{"learn":[3.725459604],"iteration":597,"passed_time":0.4896232867,"remaining_time":0.3291447512},
{"learn":[3.723158842],"iteration":598,"passed_time":0.4901871578,"remaining_time":0.3281553427},
{"learn":[3.722362756],"iteration":599,"passed_time":0.4909206573,"remaining_time":0.3272804382},
{"learn":[3.721443615],"iteration":600,"passed_time":0.4914879012,"remaining_time":0.3262956283},
{"learn":[3.720743486],"iteration":601,"passed_time":0.4920123917,"remaining_time":0.32528394},
{"learn":[3.720215334],"iteration":602,"passed_time":0.4925243286,"remaining_time":0.3242656027},
{"learn":[3.719436563],"iteration":603,"passed_time":0.4930284489,"remaining_time":0.3232438175},
{"learn":[3.715046574],"iteration":604,"passed_time":0.493570513,"remaining_time":0.3222485167},
{"learn":[3.71443396],"iteration":605,"passed_time":0.4940853802,"remaining_time":0.3212370293},
{"learn":[3.712938941],"iteration":606,"passed_time":0.4946141923,"remaining_time":0.3202362069},
{"learn":[3.712814764],"iteration":607,"passed_time":0.4952631096,"remaining_time":0.3193143733},
{"learn":[3.71235348],"iteration":608,"passed_time":0.4959093418,"remaining_time":0.3183917121},
{"learn":[3.711223749],"iteration":609,"passed_time":0.4965455773,"remaining_time":0.3174635658},
{"learn":[3.710755648],"iteration":610,"passed_time":0.4973458017,"remaining_time":0.3166407805},
{"learn":[3.708668039],"iteration":611,"passed_time":0.498604329,"remaining_time":0.3161086269},
{"learn":[3.705623591],"iteration":612,"passed_time":0.4991988828,"remaining_time":0.3151549228},
{"learn":[3.704045802],"iteration":613,"passed_time":0.4997628546,"remaining_time":0.3141831626},
{"learn":[3.699915209],"iteration":614,"passed_time":0.5002987066,"remaining_time":0.3131951253},
{"learn":[3.696182221],"iteration":615,"passed_time":0.5008550878,"remaining_time":0.3122213534},
{"learn":[3.694263278],"iteration":616,"passed_time":0.5014704034,"remaining_time":0.3112855178},
{"learn":[3.693810229],"iteration":617,"passed_time":0.5022321331,"remaining_time":0.3104412214},
{"learn":[3.690900932],"iteration":618,"passed_time":0.5029670827,"remaining_time":0.3095807084},
{"learn":[3.688020895],"iteration":619,"passed_time":0.503594826,"remaining_time":0.3086548934},
{"learn":[3.685491894],"iteration":620,"passed_time":0.504669087,"remaining_time":0.3080025507},
{"learn":[3.684328128],"iteration":621,"passed_time":0.5052340097,"remaining_time":0.3070393178},
{"learn":[3.680640153],"iteration":622,"passed_time":0.50577355,"remaining_time":0.3060620038},
{"learn":[3.678932783],"iteration":623,"passed_time":0.5063029098,"remaining_time":0.3050799585},
{"learn":[3.674167041],"iteration":624,"passed_time":0.5068347052,"remaining_time":0.3041008231},
{"learn":[3.672200976],"iteration":625,"passed_time":0.5073608657,"remaining_time":0.3031197504},
{"learn":[3.670606604],"iteration":626,"passed_time":0.508009745,"remaining_time":0.3022131338},
{"learn":[3.665506042],"iteration":627,"passed_time":0.5088137963,"remaining_time":0.3013992551},
{"learn":[3.664214007],"iteration":628,"passed_time":0.509566166,"remaining_time":0.3005549246},
{"learn":[3.66261643],"iteration":629,"passed_time":0.5101099262,"remaining_time":0.2995883693},
{"learn":[3.662118449],"iteration":630,"passed_time":0.5106267478,"remaining_time":0.2986074009},
{"learn":[3.660871366],"iteration":631,"passed_time":0.5111358651,"remaining_time":0.2976234151},
{"learn":[3.656695243],"iteration":632,"passed_time":0.5116638931,"remaining_time":0.2966518938},
{"learn":[3.654497801],"iteration":633,"passed_time":0.512179243,"remaining_time":0.2956744526},
{"learn":[3.654189134],"iteration":634,"passed_time":0.5127493232,"remaining_time":0.2947299259},
{"learn":[3.653957699],"iteration":635,"passed_time":0.5133925804,"remaining_time":0.293828458},
{"learn":[3.651920725],"iteration":636,"passed_time":0.5140469757,"remaining_time":0.2929341479},
{"learn":[3.65106705],"iteration":637,"passed_time":0.5146372799,"remaining_time":0.2920042246},
{"learn":[3.650612844],"iteration":638,"passed_time":0.5152409942,"remaining_time":0.2910829404},
{"learn":[3.649884732],"iteration":639,"passed_time":0.5161238843,"remaining_time":0.2903196849},
{"learn":[3.646276182],"iteration":640,"passed_time":0.5168041356,"remaining_time":0.2894425658},
{"learn":[3.645808194],"iteration":641,"passed_time":0.5173472632,"remaining_time":0.2884895953},
{"learn":[3.645042989],"iteration":642,"passed_time":0.517903068,"remaining_time":0.2875449382},
{"learn":[3.639864499],"iteration":643,"passed_time":0.5184541319,"remaining_time":0.2865988679},
{"learn":[3.637318478],"iteration":644,"passed_time":0.5189968008,"remaining_time":0.285649402},
{"learn":[3.636344905],"iteration":645,"passed_time":0.5199658023,"remaining_time":0.2849348205},
{"learn":[3.634754643],"iteration":646,"passed_time":0.5206681708,"remaining_time":0.2840739788},
{"learn":[3.630724975],"iteration":647,"passed_time":0.5213784365,"remaining_time":0.2832179161},
{"learn":[3.629408252],"iteration":648,"passed_time":0.5219949386,"remaining_time":0.2823115924},
{"learn":[3.62790646],"iteration":649,"passed_time":0.5229736028,"remaining_time":0.2816011707},
{"learn":[3.627388973],"iteration":650,"passed_time":0.5239156637,"remaining_time":0.2808703021},
{"learn":[3.625163557],"iteration":651,"passed_time":0.5244944432,"remaining_time":0.2799448868},
{"learn":[3.623701985],"iteration":652,"passed_time":0.5251965094,"remaining_time":0.2790860471},
{"learn":[3.622342639],"iteration":653,"passed_time":0.5258542522,"remaining_time":0.2782042374},
{"learn":[3.621130639],"iteration":654,"passed_time":0.5264988703,"remaining_time":0.2773161988},
{"learn":[3.619125665],"iteration":655,"passed_time":0.5271089335,"remaining_time":0.2764107822},
{"learn":[3.618878783],"iteration":656,"passed_time":0.5278851032,"remaining_time":0.2755929839},
{"learn":[3.616207429],"iteration":657,"passed_time":0.5286839685,"remaining_time":0.2747871083},
{"learn":[3.61206486],"iteration":658,"passed_time":0.5293262752,"remaining_time":0.2739002426},
{"learn":[3.611955873],"iteration":659,"passed_time":0.5298665102,"remaining_time":0.2729615356},
{"learn":[3.610713743],"iteration":660,"passed_time":0.530517423,"remaining_time":0.2720807964},
{"learn":[3.610044025],"iteration":661,"passed_time":0.5311255873,"remaining_time":0.2711789252},
{"learn":[3.607342669],"iteration":662,"passed_time":0.5317254373,"remaining_time":0.270273714},
{"learn":[3.602510618],"iteration":663,"passed_time":0.5323323211,"remaining_time":0.2693729818},
{"learn":[3.600492392],"iteration":664,"passed_time":0.533078514,"remaining_time":0.2685433116},
{"learn":[3.597171065],"iteration":665,"passed_time":0.5337631387,"remaining_time":0.2676830155},
{"learn":[3.594358798],"iteration":666,"passed_time":0.5345042701,"remaining_time":0.2668514572},
{"learn":[3.593945251],"iteration":667,"passed_time":0.5351266762,"remaining_time":0.2659611624},
{"learn":[3.593607748],"iteration":668,"passed_time":0.5356731683,"remaining_time":0.2650341087},
{"learn":[3.592238714],"iteration":669,"passed_time":0.5362494551,"remaining_time":0.2641228659},
{"learn":[3.590144654],"iteration":670,"passed_time":0.5369147943,"remaining_time":0.2632562851},
{"learn":[3.587151536],"iteration":671,"passed_time":0.5381843284,"remaining_time":0.2626852079},
{"learn":[3.586070865],"iteration":672,"passed_time":0.5390864879,"remaining_time":0.2619335536},
{"learn":[3.585102746],"iteration":673,"passed_time":0.5404831461,"remaining_time":0.2614206315},
{"learn":[3.584362847],"iteration":674,"passed_time":0.5412633096,"remaining_time":0.2606082602},
{"learn":[3.581407561],"iteration":675,"passed_time":0.5420284539,"remaining_time":0.2597887856},
{"learn":[3.57919422],"iteration":676,"passed_time":0.5426457094,"remaining_time":0.2588989131},
{"learn":[3.577632204],"iteration":677,"passed_time":0.5434858159,"remaining_time":0.2581156825},
{"learn":[3.573911195],"iteration":678,"passed_time":0.5441875778,"remaining_time":0.2572668814},
{"learn":[3.573408216],"iteration":679,"passed_time":0.5447760352,"remaining_time":0.256365193},
{"learn":[3.571076482],"iteration":680,"passed_time":0.5454538666,"remaining_time":0.2555062899},
{"learn":[3.568177107],"iteration":681,"passed_time":0.5464336353,"remaining_time":0.2547887039},
{"learn":[3.564824621],"iteration":682,"passed_time":0.5471151335,"remaining_time":0.2539319141},
{"learn":[3.562475026],"iteration":683,"passed_time":0.5476792907,"remaining_time":0.2530214267},
{"learn":[3.561226889],"iteration":684,"passed_time":0.5482990754,"remaining_time":0.252137531},
{"learn":[3.559383467],"iteration":685,"passed_time":0.5489703786,"remaining_time":0.2512779867},
{"learn":[3.555209766],"iteration":686,"passed_time":0.5495696329,"remaining_time":0.2503861646},
{"learn":[3.55345383],"iteration":687,"passed_time":0.5501301635,"remaining_time":0.2494776323},
{"learn":[3.552300968],"iteration":688,"passed_time":0.5506715167,"remaining_time":0.2485614538},
{"learn":[3.551253986],"iteration":689,"passed_time":0.55158238,"remaining_time":0.2478123736},
{"learn":[3.549807725],"iteration":690,"passed_time":0.5523532204,"remaining_time":0.24700021},
{"learn":[3.547992926],"iteration":691,"passed_time":0.5531089173,"remaining_time":0.2461814256},
{"learn":[3.545438607],"iteration":692,"passed_time":0.5537397506,"remaining_time":0.2453075086},
{"learn":[3.543313763],"iteration":693,"passed_time":0.5543206191,"remaining_time":0.2444122614},
{"learn":[3.542962896],"iteration":694,"passed_time":0.5548777666,"remaining_time":0.2435075091},
{"learn":[3.539800465],"iteration":695,"passed_time":0.555419925,"remaining_time":0.2425972086},
{"learn":[3.53953187],"iteration":696,"passed_time":0.5559670025,"remaining_time":0.241690103},
{"learn":[3.536332425],"iteration":697,"passed_time":0.5565102071,"remaining_time":0.2407823532},
{"learn":[3.534993327],"iteration":698,"passed_time":0.5570433612,"remaining_time":0.2398713186},
{"learn":[3.531637011],"iteration":699,"passed_time":0.5577315247,"remaining_time":0.2390277963},
{"learn":[3.531040284],"iteration":700,"passed_time":0.5600608271,"remaining_time":0.238884718},
{"learn":[3.529973872],"iteration":701,"passed_time":0.5611617016,"remaining_time":0.2382139417},
{"learn":[3.527325183],"iteration":702,"passed_time":0.5618818838,"remaining_time":0.2373811088},
{"learn":[3.527200815],"iteration":703,"passed_time":0.5625617136,"remaining_time":0.2365316296},
{"learn":[3.523459911],"iteration":704,"passed_time":0.5632294846,"remaining_time":0.2356775858},
{"learn":[3.522729934],"iteration":705,"passed_time":0.5641421607,"remaining_time":0.2349260556},
{"learn":[3.522260582],"iteration":706,"passed_time":0.5655418994,"remaining_time":0.2343759215},
{"learn":[3.518641591],"iteration":707,"passed_time":0.5662667257,"remaining_time":0.2335450338},
{"learn":[3.516856405],"iteration":708,"passed_time":0.566859436,"remaining_time":0.2326602199},
{"learn":[3.515083413],"iteration":709,"passed_time":0.5674538139,"remaining_time":0.2317769099},
{"learn":[3.514671214],"iteration":710,"passed_time":0.5680254565,"remaining_time":0.2308851715},
{"learn":[3.512617621],"iteration":711,"passed_time":0.5686465941,"remaining_time":0.2300143527},
{"learn":[3.510747971],"iteration":712,"passed_time":0.5692084628,"remaining_time":0.229120377},
{"learn":[3.508149266],"iteration":713,"passed_time":0.5697782114,"remaining_time":0.228230488},
{"learn":[3.504557165],"iteration":714,"passed_time":0.5704462892,"remaining_time":0.2273806887},
{"learn":[3.501367208],"iteration":715,"passed_time":0.571141067,"remaining_time":0.2265419875},
{"learn":[3.497593362],"iteration":716,"passed_time":0.5717309353,"remaining_time":0.2256622799},
{"learn":[3.496291169],"iteration":717,"passed_time":0.5725181785,"remaining_time":0.2248609002},
{"learn":[3.49330374],"iteration":718,"passed_time":0.5732069261,"remaining_time":0.2240210657},
{"learn":[3.490044385],"iteration":719,"passed_time":0.5742800321,"remaining_time":0.2233311236},
{"learn":[3.488891789],"iteration":720,"passed_time":0.5753197747,"remaining_time":0.2226272082},
{"learn":[3.486869081],"iteration":721,"passed_time":0.5760336608,"remaining_time":0.2217968943},
{"learn":[3.486303638],"iteration":722,"passed_time":0.5766888448,"remaining_time":0.2209444122},
{"learn":[3.486035862],"iteration":723,"passed_time":0.5774118027,"remaining_time":0.2201183115},
{"learn":[3.482668951],"iteration":724,"passed_time":0.578109693,"remaining_time":0.219282987},
{"learn":[3.47820549],"iteration":725,"passed_time":0.5787582676,"remaining_time":0.2184294288},
{"learn":[3.474392283],"iteration":726,"passed_time":0.5793279404,"remaining_time":0.2175468057},
{"learn":[3.472268163],"iteration":727,"passed_time":0.5798654725,"remaining_time":0.2166530337},
{"learn":[3.471209164],"iteration":728,"passed_time":0.580489058,"remaining_time":0.2157922287},
{"learn":[3.470049971],"iteration":729,"passed_time":0.5810616673,"remaining_time":0.2149132194},
{"learn":[3.469078654],"iteration":730,"passed_time":0.5816277454,"remaining_time":0.214032645},
{"learn":[3.468643292],"iteration":731,"passed_time":0.5823126918,"remaining_time":0.21319645},
{"learn":[3.468134848],"iteration":732,"passed_time":0.5829788548,"remaining_time":0.2123538257},
{"learn":[3.467820182],"iteration":733,"passed_time":0.5835191673,"remaining_time":0.2114660742},
{"learn":[3.465776156],"iteration":734,"passed_time":0.5842223165,"remaining_time":0.210637978},
{"learn":[3.463037608],"iteration":735,"passed_time":0.5848553,"remaining_time":0.2097850533},
{"learn":[3.45965637],"iteration":736,"passed_time":0.585394296,"remaining_time":0.2088991857},
{"learn":[3.457275091],"iteration":737,"passed_time":0.5859466391,"remaining_time":0.2080189965},
{"learn":[3.455522955],"iteration":738,"passed_time":0.5864796023,"remaining_time":0.2071328501},
{"learn":[3.451270508],"iteration":739,"passed_time":0.5870175641,"remaining_time":0.2062494144},
{"learn":[3.450978947],"iteration":740,"passed_time":0.5875339303,"remaining_time":0.205359363},
{"learn":[3.450608492],"iteration":741,"passed_time":0.5883657076,"remaining_time":0.20457999},
{"learn":[3.448122004],"iteration":742,"passed_time":0.5894894234,"remaining_time":0.203901456},
{"learn":[3.445646714],"iteration":743,"passed_time":0.5903299571,"remaining_time":0.2031242863},
{"learn":[3.44411263],"iteration":744,"passed_time":0.5913162657,"remaining_time":0.2023968426},
{"learn":[3.443264164],"iteration":745,"passed_time":0.5924036341,"remaining_time":0.201703114},
{"learn":[3.439521363],"iteration":746,"passed_time":0.593438925,"remaining_time":0.2009906935},
{"learn":[3.436809225],"iteration":747,"passed_time":0.5941469093,"remaining_time":0.2001671406},
{"learn":[3.435509465],"iteration":748,"passed_time":0.5951496053,"remaining_time":0.1994426581},
{"learn":[3.434450277],"iteration":749,"passed_time":0.5958756119,"remaining_time":0.198625204},
{"learn":[3.431786753],"iteration":750,"passed_time":0.596472314,"remaining_time":0.1977651214},
{"learn":[3.430150302],"iteration":751,"passed_time":0.5970068719,"remaining_time":0.196885245},
{"learn":[3.42696281],"iteration":752,"passed_time":0.5975643936,"remaining_time":0.1960138184},
{"learn":[3.426870334],"iteration":753,"passed_time":0.5980934956,"remaining_time":0.1951339521},
{"learn":[3.425200309],"iteration":754,"passed_time":0.5986373038,"remaining_time":0.1942597873},
{"learn":[3.423383783],"iteration":755,"passed_time":0.599156587,"remaining_time":0.193378581},
{"learn":[3.422752979],"iteration":756,"passed_time":0.5996844486,"remaining_time":0.1925010846},
{"learn":[3.420845924],"iteration":757,"passed_time":0.6002717588,"remaining_time":0.1916434903},
{"learn":[3.418917862],"iteration":758,"passed_time":0.6009331916,"remaining_time":0.1908101438},
{"learn":[3.417095735],"iteration":759,"passed_time":0.6017092889,"remaining_time":0.1900134596},
{"learn":[3.414391848],"iteration":760,"passed_time":0.6023817363,"remaining_time":0.1891842772},
{"learn":[3.41426711],"iteration":761,"passed_time":0.6033436975,"remaining_time":0.1884459318},
{"learn":[3.411976013],"iteration":762,"passed_time":0.6041552902,"remaining_time":0.1876602933},
{"learn":[3.408614844],"iteration":763,"passed_time":0.6050466668,"remaining_time":0.1868992321},
{"learn":[3.407906721],"iteration":764,"passed_time":0.6061214175,"remaining_time":0.1861941609},
{"learn":[3.407494015],"iteration":765,"passed_time":0.6067637048,"remaining_time":0.1853560142},
{"learn":[3.406287128],"iteration":766,"passed_time":0.6079188637,"remaining_time":0.1846741789},
{"learn":[3.404600442],"iteration":767,"passed_time":0.6085859719,"remaining_time":0.183843679},
{"learn":[3.404012662],"iteration":768,"passed_time":0.6091508776,"remaining_time":0.1829829034},
{"learn":[3.400398762],"iteration":769,"passed_time":0.6096910849,"remaining_time":0.1821155189},
{"learn":[3.399737714],"iteration":770,"passed_time":0.6102172082,"remaining_time":0.1812447998},
{"learn":[3.399185251],"iteration":771,"passed_time":0.6107596974,"remaining_time":0.180379807},
{"learn":[3.397245411],"iteration":772,"passed_time":0.6113256195,"remaining_time":0.1795225299},
{"learn":[3.396229831],"iteration":773,"passed_time":0.6118578214,"remaining_time":0.1786561597},
{"learn":[3.394002836],"iteration":774,"passed_time":0.6125701794,"remaining_time":0.1778429553},
{"learn":[3.389617243],"iteration":775,"passed_time":0.613427101,"remaining_time":0.1770717405},
{"learn":[3.385426488],"iteration":776,"passed_time":0.614020848,"remaining_time":0.1762247736},
{"learn":[3.385072258],"iteration":777,"passed_time":0.6145493591,"remaining_time":0.1753598428},
{"learn":[3.383842366],"iteration":778,"passed_time":0.6150752245,"remaining_time":0.1744950252},
{"learn":[3.380110746],"iteration":779,"passed_time":0.6155813829,"remaining_time":0.1736255182},
{"learn":[3.378595218],"iteration":780,"passed_time":0.6161066707,"remaining_time":0.1727623059},
{"learn":[3.377371219],"iteration":781,"passed_time":0.6166095399,"remaining_time":0.1718937081},
{"learn":[3.375814782],"iteration":782,"passed_time":0.6171348261,"remaining_time":0.171032257},
{"learn":[3.374195887],"iteration":783,"passed_time":0.6178431957,"remaining_time":0.1702221049},
{"learn":[3.373704309],"iteration":784,"passed_time":0.6197491678,"remaining_time":0.1697402179},
{"learn":[3.372971757],"iteration":785,"passed_time":0.6211787409,"remaining_time":0.1691250007},
{"learn":[3.371565136],"iteration":786,"passed_time":0.6218747355,"remaining_time":0.1683091724},
{"learn":[3.3700309],"iteration":787,"passed_time":0.6224813187,"remaining_time":0.1674695934},
{"learn":[3.368186663],"iteration":788,"passed_time":0.6231181044,"remaining_time":0.1666386819},
{"learn":[3.366710398],"iteration":789,"passed_time":0.6236826996,"remaining_time":0.165789072},
{"learn":[3.364598042],"iteration":790,"passed_time":0.6242343609,"remaining_time":0.1649367654},
{"learn":[3.36348442],"iteration":791,"passed_time":0.6249694289,"remaining_time":0.1641333854},
{"learn":[3.362001759],"iteration":792,"passed_time":0.6257619216,"remaining_time":0.1633451674},
{"learn":[3.361580401],"iteration":793,"passed_time":0.6265041501,"remaining_time":0.1625438979},
{"learn":[3.359543675],"iteration":794,"passed_time":0.6272276463,"remaining_time":0.1617379465},
{"learn":[3.35766119],"iteration":795,"passed_time":0.6279110844,"remaining_time":0.1609219362},
{"learn":[3.354592969],"iteration":796,"passed_time":0.628453074,"remaining_time":0.1600702309},
{"learn":[3.350985986],"iteration":797,"passed_time":0.6289918741,"remaining_time":0.1592184944},
{"learn":[3.349589624],"iteration":798,"passed_time":0.6295222681,"remaining_time":0.1583654266},
{"learn":[3.349110856],"iteration":799,"passed_time":0.6300590065,"remaining_time":0.1575147516},
{"learn":[3.345315441],"iteration":800,"passed_time":0.6305723212,"remaining_time":0.1566590411},
{"learn":[3.34397474],"iteration":801,"passed_time":0.6311580247,"remaining_time":0.155822056},
{"learn":[3.343800902],"iteration":802,"passed_time":0.6317880569,"remaining_time":0.1549965719},
{"learn":[3.342329465],"iteration":803,"passed_time":0.6323503503,"remaining_time":0.1541550605},
{"learn":[3.34220347],"iteration":804,"passed_time":0.6331619736,"remaining_time":0.1533746396},
{"learn":[3.341279219],"iteration":805,"passed_time":0.6339414462,"remaining_time":0.1525864027},
{"learn":[3.337329521],"iteration":806,"passed_time":0.6347768915,"remaining_time":0.1518115738},
{"learn":[3.336708453],"iteration":807,"passed_time":0.635574083,"remaining_time":0.1510275049},
{"learn":[3.333252703],"iteration":808,"passed_time":0.636407994,"remaining_time":0.1502520728},
{"learn":[3.332186769],"iteration":809,"passed_time":0.6370396069,"remaining_time":0.1494290436},
{"learn":[3.330594851],"iteration":810,"passed_time":0.637849154,"remaining_time":0.1486479533},
{"learn":[3.327867442],"iteration":811,"passed_time":0.6384728852,"remaining_time":0.1478237715},
{"learn":[3.327563111],"iteration":812,"passed_time":0.6391316432,"remaining_time":0.1470081393},
{"learn":[3.326308994],"iteration":813,"passed_time":0.6397147807,"remaining_time":0.1461756133},
{"learn":[3.326249879],"iteration":814,"passed_time":0.6402606432,"remaining_time":0.145335238},
{"learn":[3.322336238],"iteration":815,"passed_time":0.6408880353,"remaining_time":0.1445139688},
{"learn":[3.320491154],"iteration":816,"passed_time":0.6415079756,"remaining_time":0.1436915049},
{"learn":[3.320434271],"iteration":817,"passed_time":0.6420712374,"remaining_time":0.1428569257},
{"learn":[3.319609638],"iteration":818,"passed_time":0.6426860831,"remaining_time":0.1420344091},
{"learn":[3.316182682],"iteration":819,"passed_time":0.6433342776,"remaining_time":0.1412197195},
{"learn":[3.313126612],"iteration":820,"passed_time":0.6445204973,"remaining_time":0.1405227394},
{"learn":[3.311222803],"iteration":821,"passed_time":0.6451539892,"remaining_time":0.1397048784},
{"learn":[3.309627335],"iteration":822,"passed_time":0.6458554468,"remaining_time":0.1389020827},
{"learn":[3.307974895],"iteration":823,"passed_time":0.6464030799,"remaining_time":0.1380666773},
{"learn":[3.307321505],"iteration":824,"passed_time":0.6469320092,"remaining_time":0.137228002},
{"learn":[3.306759087],"iteration":825,"passed_time":0.6474602335,"remaining_time":0.1363899281},
{"learn":[3.30484037],"iteration":826,"passed_time":0.6482385349,"remaining_time":0.1356049172},
{"learn":[3.30201994],"iteration":827,"passed_time":0.6489930217,"remaining_time":0.1348149755},
{"learn":[3.299302297],"iteration":828,"passed_time":0.6499609034,"remaining_time":0.1340691369},
{"learn":[3.298132671],"iteration":829,"passed_time":0.6507252131,"remaining_time":0.1332810677},
{"learn":[3.296976183],"iteration":830,"passed_time":0.6516256868,"remaining_time":0.1325207474},
{"learn":[3.293144745],"iteration":831,"passed_time":0.6523579165,"remaining_time":0.1317261178},
{"learn":[3.290284404],"iteration":832,"passed_time":0.6530498813,"remaining_time":0.1309235656},
{"learn":[3.288285745],"iteration":833,"passed_time":0.6536728843,"remaining_time":0.1301075525},
{"learn":[3.286662667],"iteration":834,"passed_time":0.6542648888,"remaining_time":0.1292858762},
{"learn":[3.285692682],"iteration":835,"passed_time":0.6549718297,"remaining_time":0.1284872967},
{"learn":[3.284565611],"iteration":836,"passed_time":0.6555776359,"remaining_time":0.1276692409},
{"learn":[3.283897383],"iteration":837,"passed_time":0.6563716604,"remaining_time":0.1268880775},
{"learn":[3.280712855],"iteration":838,"passed_time":0.6570475316,"remaining_time":0.1260842105},
{"learn":[3.280468341],"iteration":839,"passed_time":0.6578170704,"remaining_time":0.1252984896},
{"learn":[3.277814895],"iteration":840,"passed_time":0.6585662904,"remaining_time":0.1245089657},
{"learn":[3.276316385],"iteration":841,"passed_time":0.6591225192,"remaining_time":0.1236833231},
{"learn":[3.27557063],"iteration":842,"passed_time":0.6596570751,"remaining_time":0.1228542833},
{"learn":[3.27499628],"iteration":843,"passed_time":0.6601808398,"remaining_time":0.1220239467},
{"learn":[3.273569958],"iteration":844,"passed_time":0.6607084244,"remaining_time":0.1211950364},
{"learn":[3.269665595],"iteration":845,"passed_time":0.6612527352,"remaining_time":0.1203698832},
{"learn":[3.267984685],"iteration":846,"passed_time":0.6617895014,"remaining_time":0.1195440304},
{"learn":[3.267702508],"iteration":847,"passed_time":0.6624500929,"remaining_time":0.1187410544},
{"learn":[3.266671924],"iteration":848,"passed_time":0.6631408435,"remaining_time":0.1179437778},
{"learn":[3.265359825],"iteration":849,"passed_time":0.6643947647,"remaining_time":0.1172461349},
{"learn":[3.2618983],"iteration":850,"passed_time":0.6654963297,"remaining_time":0.116520509},
{"learn":[3.260456253],"iteration":851,"passed_time":0.6666431223,"remaining_time":0.1158018569},
{"learn":[3.258389147],"iteration":852,"passed_time":0.6672807832,"remaining_time":0.1149944609},
{"learn":[3.258108469],"iteration":853,"passed_time":0.6678655444,"remaining_time":0.1141784186},
{"learn":[3.256424936],"iteration":854,"passed_time":0.6684447139,"remaining_time":0.113361969},
{"learn":[3.254817983],"iteration":855,"passed_time":0.669073483,"remaining_time":0.1125544177},
{"learn":[3.253898449],"iteration":856,"passed_time":0.6697661871,"remaining_time":0.1117579519},
{"learn":[3.253023652],"iteration":857,"passed_time":0.6703717449,"remaining_time":0.1109473051},
{"learn":[3.252845542],"iteration":858,"passed_time":0.6710206204,"remaining_time":0.1101442462},
{"learn":[3.252316026],"iteration":859,"passed_time":0.671601055,"remaining_time":0.1093304043},
{"learn":[3.24975301],"iteration":860,"passed_time":0.6721886654,"remaining_time":0.1085182631},
{"learn":[3.249151075],"iteration":861,"passed_time":0.6727552747,"remaining_time":0.1077032806},
{"learn":[3.246257135],"iteration":862,"passed_time":0.6733106556,"remaining_time":0.1068870913},
{"learn":[3.243826471],"iteration":863,"passed_time":0.6739678094,"remaining_time":0.1060875255},
{"learn":[3.243190653],"iteration":864,"passed_time":0.6745554723,"remaining_time":0.1052774437},
{"learn":[3.24008797],"iteration":865,"passed_time":0.6753374139,"remaining_time":0.104497937},
{"learn":[3.240036811],"iteration":866,"passed_time":0.6760482377,"remaining_time":0.1037075151},
{"learn":[3.238676314],"iteration":867,"passed_time":0.6765935972,"remaining_time":0.1028921139},
{"learn":[3.237848782],"iteration":868,"passed_time":0.6771173594,"remaining_time":0.1020740783},
{"learn":[3.236405498],"iteration":869,"passed_time":0.6776528174,"remaining_time":0.101258467},
{"learn":[3.233378068],"iteration":870,"passed_time":0.6781806537,"remaining_time":0.1004423701},
{"learn":[3.233169169],"iteration":871,"passed_time":0.6790857811,"remaining_time":0.09968231649},
{"learn":[3.232434885],"iteration":872,"passed_time":0.6798052478,"remaining_time":0.09889492151},
{"learn":[3.229978115],"iteration":873,"passed_time":0.6807669014,"remaining_time":0.09814259677},
{"learn":[3.229648848],"iteration":874,"passed_time":0.681684885,"remaining_time":0.09738355499},
{"learn":[3.227208761],"iteration":875,"passed_time":0.6824945724,"remaining_time":0.09660882075},
{"learn":[3.226258869],"iteration":876,"passed_time":0.6831179406,"remaining_time":0.09580787536},
{"learn":[3.225331995],"iteration":877,"passed_time":0.6838264845,"remaining_time":0.09501916983},
{"learn":[3.221968268],"iteration":878,"passed_time":0.6844053961,"remaining_time":0.09421280196},
{"learn":[3.221166317],"iteration":879,"passed_time":0.6850239412,"remaining_time":0.09341235562},
{"learn":[3.220047503],"iteration":880,"passed_time":0.6856061961,"remaining_time":0.09260742036},
{"learn":[3.21982781],"iteration":881,"passed_time":0.6861671755,"remaining_time":0.09180014366},
{"learn":[3.216693405],"iteration":882,"passed_time":0.686712181,"remaining_time":0.09099130824},
{"learn":[3.214798761],"iteration":883,"passed_time":0.6879270287,"remaining_time":0.09027096756},
{"learn":[3.214395085],"iteration":884,"passed_time":0.6892238238,"remaining_time":0.0895601579},
{"learn":[3.213470696],"iteration":885,"passed_time":0.6899315998,"remaining_time":0.08877223745},
{"learn":[3.211595017],"iteration":886,"passed_time":0.6904928438,"remaining_time":0.08796583015},
{"learn":[3.210965255],"iteration":887,"passed_time":0.6910459759,"remaining_time":0.08715895192},
{"learn":[3.209413583],"iteration":888,"passed_time":0.6915878433,"remaining_time":0.08635123803},
{"learn":[3.208331683],"iteration":889,"passed_time":0.6922019778,"remaining_time":0.08555305343},
{"learn":[3.207110711],"iteration":890,"passed_time":0.6928371187,"remaining_time":0.08475785178},
{"learn":[3.204519413],"iteration":891,"passed_time":0.6938952468,"remaining_time":0.0840142227},
{"learn":[3.201421296],"iteration":892,"passed_time":0.6945668427,"remaining_time":0.08322357465},
{"learn":[3.200691259],"iteration":893,"passed_time":0.6955598802,"remaining_time":0.08247130571},
{"learn":[3.200485067],"iteration":894,"passed_time":0.6965287427,"remaining_time":0.08171566255},
{"learn":[3.197467568],"iteration":895,"passed_time":0.6973814403,"remaining_time":0.08094606004},
{"learn":[3.195838544],"iteration":896,"passed_time":0.6980554502,"remaining_time":0.08015575404},
{"learn":[3.195671746],"iteration":897,"passed_time":0.6986381729,"remaining_time":0.07935533813},
{"learn":[3.194213094],"iteration":898,"passed_time":0.6992483799,"remaining_time":0.07855849429},
{"learn":[3.192884691],"iteration":899,"passed_time":0.6998462982,"remaining_time":0.0777606998},
{"learn":[3.188364239],"iteration":900,"passed_time":0.7003723333,"remaining_time":0.0769554506},
{"learn":[3.185219478],"iteration":901,"passed_time":0.7009466163,"remaining_time":0.07615606253},
{"learn":[3.184120387],"iteration":902,"passed_time":0.701484526,"remaining_time":0.0753532658},
{"learn":[3.183725321],"iteration":903,"passed_time":0.7020149585,"remaining_time":0.07455026107},
{"learn":[3.181264554],"iteration":904,"passed_time":0.7025706151,"remaining_time":0.07375050656},
{"learn":[3.180741589],"iteration":905,"passed_time":0.7031030712,"remaining_time":0.07294888377},
{"learn":[3.179782639],"iteration":906,"passed_time":0.7036205606,"remaining_time":0.07214631989},
{"learn":[3.176377564],"iteration":907,"passed_time":0.7041542032,"remaining_time":0.07134602059},
{"learn":[3.174078182],"iteration":908,"passed_time":0.7047477941,"remaining_time":0.07055230942},
{"learn":[3.171242379],"iteration":909,"passed_time":0.7053554107,"remaining_time":0.06976042523},
{"learn":[3.170421012],"iteration":910,"passed_time":0.7059382862,"remaining_time":0.06896652851},
{"learn":[3.170087224],"iteration":911,"passed_time":0.7065183656,"remaining_time":0.06817282475},
{"learn":[3.167303059],"iteration":912,"passed_time":0.7072233943,"remaining_time":0.0673914954},
{"learn":[3.16705966],"iteration":913,"passed_time":0.7078932394,"remaining_time":0.06660702253},
{"learn":[3.165667683],"iteration":914,"passed_time":0.7092456724,"remaining_time":0.06588621},
{"learn":[3.164689733],"iteration":915,"passed_time":0.710469459,"remaining_time":0.06515222113},
{"learn":[3.163311455],"iteration":916,"passed_time":0.7112586765,"remaining_time":0.06437783005},
{"learn":[3.159425016],"iteration":917,"passed_time":0.7121615444,"remaining_time":0.06361355843},
{"learn":[3.159327058],"iteration":918,"passed_time":0.712991226,"remaining_time":0.06284253461},
{"learn":[3.15819426],"iteration":919,"passed_time":0.7136405284,"remaining_time":0.06205569812},
{"learn":[3.157086603],"iteration":920,"passed_time":0.7141850838,"remaining_time":0.06126017549},
{"learn":[3.153354154],"iteration":921,"passed_time":0.7147236861,"remaining_time":0.06046469362},
{"learn":[3.153261317],"iteration":922,"passed_time":0.7152276603,"remaining_time":0.05966687957},
{"learn":[3.153168454],"iteration":923,"passed_time":0.7157297355,"remaining_time":0.05886954534},
{"learn":[3.152080399],"iteration":924,"passed_time":0.7162534936,"remaining_time":0.05807460759},
{"learn":[3.151635144],"iteration":925,"passed_time":0.7167683665,"remaining_time":0.05727954549},
{"learn":[3.147762655],"iteration":926,"passed_time":0.7173845958,"remaining_time":0.05649306957},
{"learn":[3.147172317],"iteration":927,"passed_time":0.7181824571,"remaining_time":0.05572105271},
{"learn":[3.146254125],"iteration":928,"passed_time":0.7187551699,"remaining_time":0.05493177294},
{"learn":[3.144869828],"iteration":929,"passed_time":0.7193585021,"remaining_time":0.0541452636},
{"learn":[3.143466218],"iteration":930,"passed_time":0.7199166005,"remaining_time":0.05335579531},
{"learn":[3.141919643],"iteration":931,"passed_time":0.7204566049,"remaining_time":0.05256550336},
{"learn":[3.141054135],"iteration":932,"passed_time":0.7209800964,"remaining_time":0.05177456212},
{"learn":[3.139390417],"iteration":933,"passed_time":0.7214954194,"remaining_time":0.05098361636},
{"learn":[3.139025283],"iteration":934,"passed_time":0.7220007084,"remaining_time":0.05019256262},
{"learn":[3.137824183],"iteration":935,"passed_time":0.7225661329,"remaining_time":0.04940623131},
{"learn":[3.135620453],"iteration":936,"passed_time":0.723688357,"remaining_time":0.04865780842},
{"learn":[3.13443178],"iteration":937,"passed_time":0.7244306849,"remaining_time":0.04788347811},
{"learn":[3.132765713],"iteration":938,"passed_time":0.7250504733,"remaining_time":0.04710125545},
{"learn":[3.131434124],"iteration":939,"passed_time":0.7259218689,"remaining_time":0.04633543844},
{"learn":[3.128384262],"iteration":940,"passed_time":0.7267616475,"remaining_time":0.04556741467},
{"learn":[3.128120455],"iteration":941,"passed_time":0.7274992691,"remaining_time":0.04479294863},
{"learn":[3.126314615],"iteration":942,"passed_time":0.7280788057,"remaining_time":0.04400900522},
{"learn":[3.125409666],"iteration":943,"passed_time":0.7286804914,"remaining_time":0.04322680881},
{"learn":[3.123072589],"iteration":944,"passed_time":0.7293158856,"remaining_time":0.04244695631},
{"learn":[3.122921099],"iteration":945,"passed_time":0.7299829413,"remaining_time":0.04166921652},
{"learn":[3.122182662],"iteration":946,"passed_time":0.7306073941,"remaining_time":0.04088932617},
{"learn":[3.120040951],"iteration":947,"passed_time":0.7312599517,"remaining_time":0.04011130537},
{"learn":[3.118767799],"iteration":948,"passed_time":0.731943283,"remaining_time":0.03933520278},
{"learn":[3.118203218],"iteration":949,"passed_time":0.7325459168,"remaining_time":0.03855504825},
{"learn":[3.116343362],"iteration":950,"passed_time":0.7331678803,"remaining_time":0.03777626302},
{"learn":[3.11480829],"iteration":951,"passed_time":0.7337211118,"remaining_time":0.03699434177},
{"learn":[3.112607903],"iteration":952,"passed_time":0.7342568484,"remaining_time":0.03621203764},
{"learn":[3.111661241],"iteration":953,"passed_time":0.7347839706,"remaining_time":0.03542983506},
{"learn":[3.110249676],"iteration":954,"passed_time":0.7353121025,"remaining_time":0.03464821425},
{"learn":[3.107333579],"iteration":955,"passed_time":0.7358401686,"remaining_time":0.03386712073},
{"learn":[3.107149851],"iteration":956,"passed_time":0.736392758,"remaining_time":0.03308765788},
{"learn":[3.106867336],"iteration":957,"passed_time":0.7369068871,"remaining_time":0.03230698252},
{"learn":[3.10364681],"iteration":958,"passed_time":0.7375009569,"remaining_time":0.03153028074},
{"learn":[3.102703811],"iteration":959,"passed_time":0.7380450707,"remaining_time":0.03075187794},
{"learn":[3.101469264],"iteration":960,"passed_time":0.7388073232,"remaining_time":0.02998281541},
{"learn":[3.09863569],"iteration":961,"passed_time":0.7395454147,"remaining_time":0.02921281264},
{"learn":[3.09645939],"iteration":962,"passed_time":0.7404792094,"remaining_time":0.02845039538},
{"learn":[3.096240186],"iteration":963,"passed_time":0.7412373394,"remaining_time":0.02768106247},
{"learn":[3.094838828],"iteration":964,"passed_time":0.7418175786,"remaining_time":0.02690530078},
{"learn":[3.094176802],"iteration":965,"passed_time":0.7424243688,"remaining_time":0.02613087841},
{"learn":[3.093182279],"iteration":966,"passed_time":0.7432090126,"remaining_time":0.0253628722},
{"learn":[3.090150687],"iteration":967,"passed_time":0.7437899804,"remaining_time":0.02458809853},
{"learn":[3.088612829],"iteration":968,"passed_time":0.7443481119,"remaining_time":0.02381299429},
{"learn":[3.087153684],"iteration":969,"passed_time":0.7448720418,"remaining_time":0.02303727964},
{"learn":[3.085866843],"iteration":970,"passed_time":0.7454179068,"remaining_time":0.02226273872},
{"learn":[3.082669094],"iteration":971,"passed_time":0.7459503865,"remaining_time":0.02148828274},
{"learn":[3.081047548],"iteration":972,"passed_time":0.7464911241,"remaining_time":0.02071455329},
{"learn":[3.079684322],"iteration":973,"passed_time":0.7470355922,"remaining_time":0.01994140184},
{"learn":[3.07613431],"iteration":974,"passed_time":0.7475670158,"remaining_time":0.01916838502},
{"learn":[3.074005935],"iteration":975,"passed_time":0.7480991581,"remaining_time":0.01839588094},
{"learn":[3.072988853],"iteration":976,"passed_time":0.7486565026,"remaining_time":0.01762446219},
{"learn":[3.072344268],"iteration":977,"passed_time":0.7492278368,"remaining_time":0.01685379592},
{"learn":[3.070654438],"iteration":978,"passed_time":0.7497655353,"remaining_time":0.01608281536},
{"learn":[3.069724506],"iteration":979,"passed_time":0.7503380543,"remaining_time":0.01531302152},
{"learn":[3.067763166],"iteration":980,"passed_time":0.7509079255,"remaining_time":0.01454357858},
{"learn":[3.066737893],"iteration":981,"passed_time":0.7514940413,"remaining_time":0.01377483986},
{"learn":[3.065248174],"iteration":982,"passed_time":0.7520453991,"remaining_time":0.0130058716},
{"learn":[3.063186837],"iteration":983,"passed_time":0.7525588044,"remaining_time":0.01223672853},
{"learn":[3.062880371],"iteration":984,"passed_time":0.7530795975,"remaining_time":0.01146821722},
{"learn":[3.061288645],"iteration":985,"passed_time":0.7538843175,"remaining_time":0.0107042398},
{"learn":[3.059970575],"iteration":986,"passed_time":0.7545729256,"remaining_time":0.009938650489},
{"learn":[3.059576341],"iteration":987,"passed_time":0.7552024399,"remaining_time":0.00917249927},
{"learn":[3.058175919],"iteration":988,"passed_time":0.7562646557,"remaining_time":0.00841143702},
{"learn":[3.056830702],"iteration":989,"passed_time":0.7569189666,"remaining_time":0.007645646127},
{"learn":[3.056336579],"iteration":990,"passed_time":0.7574438723,"remaining_time":0.006878904995},
{"learn":[3.055810414],"iteration":991,"passed_time":0.757965926,"remaining_time":0.006112628435},
{"learn":[3.055476518],"iteration":992,"passed_time":0.7584799536,"remaining_time":0.005346787185},
{"learn":[3.053331734],"iteration":993,"passed_time":0.7590175502,"remaining_time":0.00458159487},
{"learn":[3.050890374],"iteration":994,"passed_time":0.7595536283,"remaining_time":0.003816852404},
{"learn":[3.04972623],"iteration":995,"passed_time":0.7600846425,"remaining_time":0.003052548765},
{"learn":[3.047217327],"iteration":996,"passed_time":0.7606045256,"remaining_time":0.002288679616},
{"learn":[3.047155483],"iteration":997,"passed_time":0.7611515033,"remaining_time":0.001525353714},
{"learn":[3.04430671],"iteration":998,"passed_time":0.7617539218,"remaining_time":0.0007625164382},
{"learn":[3.042664195],"iteration":999,"passed_time":0.7623719105,"remaining_time":0}
]}